package com.laiqian.main.module.settlement.pay;

import com.laiqian.entity.v;
import com.laiqian.main.b.c;
import io.reactivex.c.c;
import java.util.List;

class k extends Object implements c<List<c>, List<v>, c> {
  k(PosActivitySettlementDialogPayTypeFragment paramPosActivitySettlementDialogPayTypeFragment) {}
  
  public c c(List<c> paramList1, List<v> paramList2) throws Exception { // Byte code:
    //   0: ldc '@emery payTypeFragment'
    //   2: ldc '-----初始化支付方式不包含,默认选中现金-------'
    //   4: invokestatic i : (Ljava/lang/String;Ljava/lang/String;)I
    //   7: pop
    //   8: getstatic com/laiqian/main/b/c.bpu : Lcom/laiqian/main/b/c;
    //   11: astore #6
    //   13: aload_2
    //   14: invokeinterface size : ()I
    //   19: aload_1
    //   20: invokeinterface size : ()I
    //   25: invokestatic min : (II)I
    //   28: istore #4
    //   30: iconst_0
    //   31: istore_3
    //   32: iload_3
    //   33: iload #4
    //   35: if_icmpge -> 442
    //   38: aload_2
    //   39: iload_3
    //   40: invokeinterface get : (I)Ljava/lang/Object;
    //   45: checkcast com/laiqian/entity/v
    //   48: astore #9
    //   50: aload_1
    //   51: iload_3
    //   52: invokeinterface get : (I)Ljava/lang/Object;
    //   57: checkcast com/laiqian/main/b/c
    //   60: astore #8
    //   62: aload_0
    //   63: getfield boK : Lcom/laiqian/main/module/settlement/pay/PosActivitySettlementDialogPayTypeFragment;
    //   66: getfield blQ : Lcom/laiqian/main/module/settlement/ag;
    //   69: getfield bmC : Lcom/jakewharton/b/b;
    //   72: invokevirtual getValue : ()Ljava/lang/Object;
    //   75: checkcast com/laiqian/entity/aq
    //   78: invokestatic a : (Lcom/laiqian/entity/aq;)Z
    //   81: ifne -> 107
    //   84: aload #9
    //   86: getfield aSX : I
    //   89: sipush #10006
    //   92: if_icmpne -> 107
    //   95: aload #8
    //   97: getfield view : Landroid/view/View;
    //   100: iconst_1
    //   101: invokevirtual setSelected : (Z)V
    //   104: goto -> 157
    //   107: aload #6
    //   109: astore #7
    //   111: aload_0
    //   112: getfield boK : Lcom/laiqian/main/module/settlement/pay/PosActivitySettlementDialogPayTypeFragment;
    //   115: getfield blQ : Lcom/laiqian/main/module/settlement/ag;
    //   118: getfield bmC : Lcom/jakewharton/b/b;
    //   121: invokevirtual getValue : ()Ljava/lang/Object;
    //   124: checkcast com/laiqian/entity/aq
    //   127: invokestatic a : (Lcom/laiqian/entity/aq;)Z
    //   130: ifeq -> 161
    //   133: aload #6
    //   135: astore #7
    //   137: aload #9
    //   139: getfield aSX : I
    //   142: sipush #10001
    //   145: if_icmpne -> 161
    //   148: aload #8
    //   150: getfield view : Landroid/view/View;
    //   153: iconst_1
    //   154: invokevirtual setSelected : (Z)V
    //   157: aload #8
    //   159: astore #7
    //   161: aload #9
    //   163: getfield aSX : I
    //   166: istore #5
    //   168: iload #5
    //   170: sipush #10001
    //   173: if_icmpeq -> 400
    //   176: iload #5
    //   178: tableswitch default -> 216, 10006 -> 400, 10007 -> 333, 10008 -> 400, 10009 -> 266, 10010 -> 400, 10011 -> 400
    //   216: iload #5
    //   218: tableswitch default -> 240, 10013 -> 243, 10014 -> 400
    //   240: goto -> 431
    //   243: aload #8
    //   245: aload #9
    //   247: getfield aTa : I
    //   250: aload #9
    //   252: getfield name : Ljava/lang/String;
    //   255: aload #9
    //   257: getfield aSW : J
    //   260: invokevirtual a : (ILjava/lang/String;J)V
    //   263: goto -> 431
    //   266: aload #8
    //   268: aload #9
    //   270: getfield aSX : I
    //   273: aload #9
    //   275: getfield aTb : I
    //   278: aload #9
    //   280: getfield name : Ljava/lang/String;
    //   283: aload #9
    //   285: getfield aTe : J
    //   288: aload #9
    //   290: getfield aTc : I
    //   293: aload #9
    //   295: getfield aTd : Ljava/lang/String;
    //   298: invokevirtual a : (IILjava/lang/String;JILjava/lang/String;)V
    //   301: aload_0
    //   302: getfield boK : Lcom/laiqian/main/module/settlement/pay/PosActivitySettlementDialogPayTypeFragment;
    //   305: getfield blQ : Lcom/laiqian/main/module/settlement/ag;
    //   308: getfield bmT : Lcom/laiqian/main/module/settlement/ag$a;
    //   311: getfield bnw : Ljava/util/Map;
    //   314: aload #9
    //   316: getfield aSX : I
    //   319: invokestatic valueOf : (I)Ljava/lang/Integer;
    //   322: aload #8
    //   324: invokeinterface put : (Ljava/lang/Object;Ljava/lang/Object;)Ljava/lang/Object;
    //   329: pop
    //   330: goto -> 431
    //   333: aload #8
    //   335: aload #9
    //   337: getfield aSX : I
    //   340: aload #9
    //   342: getfield aTb : I
    //   345: aload #9
    //   347: getfield name : Ljava/lang/String;
    //   350: aload #9
    //   352: getfield aTe : J
    //   355: aload #9
    //   357: getfield aTc : I
    //   360: aload #9
    //   362: getfield aTd : Ljava/lang/String;
    //   365: invokevirtual a : (IILjava/lang/String;JILjava/lang/String;)V
    //   368: aload_0
    //   369: getfield boK : Lcom/laiqian/main/module/settlement/pay/PosActivitySettlementDialogPayTypeFragment;
    //   372: getfield blQ : Lcom/laiqian/main/module/settlement/ag;
    //   375: getfield bmT : Lcom/laiqian/main/module/settlement/ag$a;
    //   378: getfield bnw : Ljava/util/Map;
    //   381: aload #9
    //   383: getfield aSX : I
    //   386: invokestatic valueOf : (I)Ljava/lang/Integer;
    //   389: aload #8
    //   391: invokeinterface put : (Ljava/lang/Object;Ljava/lang/Object;)Ljava/lang/Object;
    //   396: pop
    //   397: goto -> 431
    //   400: aload #8
    //   402: aload #9
    //   404: getfield aSX : I
    //   407: aload #9
    //   409: getfield aTb : I
    //   412: aload #9
    //   414: getfield name : Ljava/lang/String;
    //   417: lconst_0
    //   418: aload #9
    //   420: getfield aTc : I
    //   423: aload #9
    //   425: getfield aTd : Ljava/lang/String;
    //   428: invokevirtual a : (IILjava/lang/String;JILjava/lang/String;)V
    //   431: iload_3
    //   432: iconst_1
    //   433: iadd
    //   434: istore_3
    //   435: aload #7
    //   437: astore #6
    //   439: goto -> 32
    //   442: aload #6
    //   444: areturn }
}


/* Location:              F:\chrome_download\android-Decompile\dex2jar-2.0\classes-dex2jar.jar!\com\laiqian\main\module\settlement\pay\k.class
 * Java compiler version: 6 (50.0)
 * JD-Core Version:       1.0.4
 */