package com.laiqian.product;

class ar implements bq.a {
  ar(ProductAttributeActivity paramProductAttributeActivity) {}
  
  public void a(boolean paramBoolean, String paramString1, String paramString2, String paramString3, String paramString4) { this.cPC.cPw.aju(); }
  
  public void b(boolean paramBoolean, String paramString1, String paramString2, String paramString3, String paramString4) { // Byte code:
    //   0: aload_0
    //   1: getfield cPC : Lcom/laiqian/product/ProductAttributeActivity;
    //   4: getfield cPw : Lcom/laiqian/product/ProductAttributeActivity$d;
    //   7: aload_2
    //   8: invokestatic parseLong : (Ljava/lang/String;)J
    //   11: invokevirtual cE : (J)V
    //   14: aload #4
    //   16: invokevirtual hashCode : ()I
    //   19: istore #6
    //   21: iload #6
    //   23: bipush #48
    //   25: if_icmpeq -> 54
    //   28: iload #6
    //   30: bipush #52
    //   32: if_icmpeq -> 38
    //   35: goto -> 70
    //   38: aload #4
    //   40: ldc '4'
    //   42: invokevirtual equals : (Ljava/lang/Object;)Z
    //   45: ifeq -> 70
    //   48: iconst_1
    //   49: istore #6
    //   51: goto -> 73
    //   54: aload #4
    //   56: ldc '0'
    //   58: invokevirtual equals : (Ljava/lang/Object;)Z
    //   61: ifeq -> 70
    //   64: iconst_0
    //   65: istore #6
    //   67: goto -> 73
    //   70: iconst_m1
    //   71: istore #6
    //   73: iload #6
    //   75: tableswitch default -> 96, 0 -> 118, 1 -> 107
    //   96: aload_0
    //   97: getfield cPC : Lcom/laiqian/product/ProductAttributeActivity;
    //   100: getfield cPw : Lcom/laiqian/product/ProductAttributeActivity$d;
    //   103: invokevirtual ajx : ()V
    //   106: return
    //   107: aload_0
    //   108: getfield cPC : Lcom/laiqian/product/ProductAttributeActivity;
    //   111: getfield cPw : Lcom/laiqian/product/ProductAttributeActivity$d;
    //   114: invokevirtual ajw : ()V
    //   117: return
    //   118: aload_0
    //   119: getfield cPC : Lcom/laiqian/product/ProductAttributeActivity;
    //   122: getfield cPw : Lcom/laiqian/product/ProductAttributeActivity$d;
    //   125: invokevirtual ajv : ()V
    //   128: return }
  
  public void c(boolean paramBoolean, String paramString1, String paramString2, String paramString3, String paramString4) { // Byte code:
    //   0: aload #4
    //   2: invokevirtual hashCode : ()I
    //   5: istore #6
    //   7: iload #6
    //   9: bipush #48
    //   11: if_icmpeq -> 40
    //   14: iload #6
    //   16: bipush #52
    //   18: if_icmpeq -> 24
    //   21: goto -> 56
    //   24: aload #4
    //   26: ldc '4'
    //   28: invokevirtual equals : (Ljava/lang/Object;)Z
    //   31: ifeq -> 56
    //   34: iconst_1
    //   35: istore #6
    //   37: goto -> 59
    //   40: aload #4
    //   42: ldc '0'
    //   44: invokevirtual equals : (Ljava/lang/Object;)Z
    //   47: ifeq -> 56
    //   50: iconst_0
    //   51: istore #6
    //   53: goto -> 59
    //   56: iconst_m1
    //   57: istore #6
    //   59: iload #6
    //   61: tableswitch default -> 84, 0 -> 106, 1 -> 95
    //   84: aload_0
    //   85: getfield cPC : Lcom/laiqian/product/ProductAttributeActivity;
    //   88: getfield cPw : Lcom/laiqian/product/ProductAttributeActivity$d;
    //   91: invokevirtual ajx : ()V
    //   94: return
    //   95: aload_0
    //   96: getfield cPC : Lcom/laiqian/product/ProductAttributeActivity;
    //   99: getfield cPw : Lcom/laiqian/product/ProductAttributeActivity$d;
    //   102: invokevirtual ajw : ()V
    //   105: return
    //   106: aload_0
    //   107: getfield cPC : Lcom/laiqian/product/ProductAttributeActivity;
    //   110: getfield cPw : Lcom/laiqian/product/ProductAttributeActivity$d;
    //   113: invokevirtual ajv : ()V
    //   116: return }
}


/* Location:              F:\chrome_download\android-Decompile\dex2jar-2.0\classes2-dex2jar.jar!\com\laiqian\product\ar.class
 * Java compiler version: 6 (50.0)
 * JD-Core Version:       1.0.4
 */