package com.laiqian.pos.settings;

import com.laiqian.ui.container.LayoutLeftTextRightTextWithDialog;
import kotlin.Metadata;

@Metadata
final class aw implements LayoutLeftTextRightTextWithDialog.b {
  aw(ShopBasicInfoFragment paramShopBasicInfoFragment) {}
  
  public final void h(int paramInt, String paramString) { // Byte code:
    //   0: iload_1
    //   1: tableswitch default -> 24, 0 -> 38, 1 -> 25
    //   24: return
    //   25: aload_0
    //   26: getfield cAE : Lcom/laiqian/pos/settings/ShopBasicInfoFragment;
    //   29: invokestatic b : (Lcom/laiqian/pos/settings/ShopBasicInfoFragment;)Lcom/laiqian/pos/settings/cs;
    //   32: iconst_2
    //   33: invokevirtual hu : (I)Z
    //   36: pop
    //   37: return
    //   38: aload_0
    //   39: getfield cAE : Lcom/laiqian/pos/settings/ShopBasicInfoFragment;
    //   42: invokestatic b : (Lcom/laiqian/pos/settings/ShopBasicInfoFragment;)Lcom/laiqian/pos/settings/cs;
    //   45: iconst_1
    //   46: invokevirtual hu : (I)Z
    //   49: pop
    //   50: return
    //   51: astore_2
    //   52: aload_2
    //   53: invokestatic e : (Ljava/lang/Throwable;)V
    //   56: return
    // Exception table:
    //   from	to	target	type
    //   25	37	51	java/lang/Exception
    //   38	50	51	java/lang/Exception }
}


/* Location:              F:\chrome_download\android-Decompile\dex2jar-2.0\classes2-dex2jar.jar!\com\laiqian\pos\settings\aw.class
 * Java compiler version: 6 (50.0)
 * JD-Core Version:       1.0.4
 */