package com.laiqian.pos.hardware;

import java.util.ArrayList;

public class RootUrlParameter {
  public static String agL;
  
  public static String agM;
  
  public static final boolean bDebug;
  
  public static int ckA = 0;
  
  public static final String ckB;
  
  public static final String ckC;
  
  public static final String ckD;
  
  public static final String ckE;
  
  public static final String ckF;
  
  public static final String ckG;
  
  public static final String ckH;
  
  public static String ckI = "";
  
  public static String ckJ;
  
  @ServerType
  public static final int ckK;
  
  public static final boolean ckL;
  
  public static String ckM;
  
  public static String ckN = "";
  
  private static String ckO = "http://hotpatch-singapore.91laiqian.cn";
  
  private static String ckP = "http://hotpatch-pre-slb.91laiqian.cn";
  
  private static String ckQ = "http://hotpatch.91laiqian.cn";
  
  private static String ckR = "";
  
  public static String ckS;
  
  public static String ckT;
  
  public static String ckU;
  
  public static String ckV;
  
  public static String ckW;
  
  public static String ckX;
  
  public static final String ckY;
  
  public static final String ckZ;
  
  public static int ckz = 1;
  
  public static String clA;
  
  public static String clB;
  
  public static String clC;
  
  public static String clD;
  
  public static String clE;
  
  public static String clF;
  
  public static String clG;
  
  public static String clH;
  
  public static String clI;
  
  public static String clJ;
  
  public static String clK;
  
  public static String clL;
  
  public static String clM;
  
  public static String clN;
  
  public static String clO;
  
  public static String clP;
  
  public static final String clQ;
  
  public static String clR;
  
  public static String clS;
  
  public static final String clT;
  
  public static String clU;
  
  public static final String clV;
  
  public static final String clW;
  
  public static final String clX;
  
  public static final String clY;
  
  public static final String clZ;
  
  public static String cla;
  
  public static int clb = 0;
  
  public static String clc = "";
  
  public static final String cld;
  
  public static final String cle;
  
  public static final String clf;
  
  public static final String clg;
  
  public static final String clh;
  
  public static final String cli;
  
  public static final String clj;
  
  public static String clk = "http://pre-file.91laiqian.com/";
  
  public static final String cll;
  
  public static ArrayList clm;
  
  public static String cln;
  
  public static final String clo;
  
  public static final String clp;
  
  public static final String clq;
  
  public static final String clr;
  
  public static final String cls;
  
  public static String clt;
  
  public static String clu;
  
  public static String clv;
  
  public static String clw;
  
  public static String clx;
  
  public static String cly;
  
  public static String clz;
  
  public static final String cmA;
  
  public static final String cmB;
  
  public static final String cma;
  
  public static final String cmb;
  
  public static final String cmc;
  
  public static final String cme;
  
  public static final String cmf;
  
  public static final String cmg;
  
  public static final String cmh;
  
  public static final String cmi;
  
  public static final String cmj;
  
  public static final String cmk;
  
  public static final String cml;
  
  public static final String cmm;
  
  public static final String cmn;
  
  public static final String cmo;
  
  public static final String cmp;
  
  public static final String cmq;
  
  public static final String cmr;
  
  public static final String cms;
  
  public static String cmt;
  
  public static String cmu;
  
  public static String cmv;
  
  public static final String cmw;
  
  public static final String cmx;
  
  public static final String cmy;
  
  public static final String cmz;
  
  static  {
    // Byte code:
    //   0: getstatic com/laiqian/pos/hardware/RootUrlParameter.ckz : I
    //   3: putstatic com/laiqian/pos/hardware/RootUrlParameter.ckA : I
    //   6: invokestatic zg : ()Z
    //   9: putstatic com/laiqian/pos/hardware/RootUrlParameter.bDebug : Z
    //   12: invokestatic zg : ()Z
    //   15: putstatic com/laiqian/pos/hardware/RootUrlParameter.ckL : Z
    //   18: new java/util/ArrayList
    //   21: dup
    //   22: invokespecial <init> : ()V
    //   25: putstatic com/laiqian/pos/hardware/RootUrlParameter.clm : Ljava/util/ArrayList;
    //   28: invokestatic zp : ()I
    //   31: putstatic com/laiqian/pos/hardware/RootUrlParameter.ckK : I
    //   34: getstatic com/laiqian/pos/hardware/RootUrlParameter.ckK : I
    //   37: tableswitch default -> 100, 3 -> 1388, 4 -> 1273, 5 -> 1159, 6 -> 1044, 7 -> 100, 8 -> 915, 9 -> 798, 10 -> 673, 11 -> 565, 12 -> 440, 13 -> 320, 14 -> 200
    //   100: ldc 'http://91laiqian-cdn-image.oss-cn-qingdao.aliyuncs.com/'
    //   102: putstatic com/laiqian/pos/hardware/RootUrlParameter.cll : Ljava/lang/String;
    //   105: getstatic com/laiqian/pos/hardware/RootUrlParameter.ckQ : Ljava/lang/String;
    //   108: putstatic com/laiqian/pos/hardware/RootUrlParameter.ckN : Ljava/lang/String;
    //   111: ldc 'https://wallet20180329.91laiqian.com/'
    //   113: putstatic com/laiqian/pos/hardware/RootUrlParameter.ckS : Ljava/lang/String;
    //   116: ldc 'http://online.91laiqian.com/'
    //   118: putstatic com/laiqian/pos/hardware/RootUrlParameter.ckC : Ljava/lang/String;
    //   121: ldc 'http://open-table.91laiqian.com/'
    //   123: putstatic com/laiqian/pos/hardware/RootUrlParameter.ckD : Ljava/lang/String;
    //   126: ldc 'http://user.91laiqian.com'
    //   128: putstatic com/laiqian/pos/hardware/RootUrlParameter.ckI : Ljava/lang/String;
    //   131: ldc 'http://channel.91laiqian.com'
    //   133: putstatic com/laiqian/pos/hardware/RootUrlParameter.ckY : Ljava/lang/String;
    //   136: ldc 'download.91laiqian.com'
    //   138: putstatic com/laiqian/pos/hardware/RootUrlParameter.ckZ : Ljava/lang/String;
    //   141: ldc 'http://online.91laiqian.com/transaction/index'
    //   143: putstatic com/laiqian/pos/hardware/RootUrlParameter.cla : Ljava/lang/String;
    //   146: ldc 'https://ta.91laiqian.com/'
    //   148: putstatic com/laiqian/pos/hardware/RootUrlParameter.ckV : Ljava/lang/String;
    //   151: ldc 'https://order.91laiqian.com/'
    //   153: putstatic com/laiqian/pos/hardware/RootUrlParameter.ckW : Ljava/lang/String;
    //   156: ldc 100114
    //   158: putstatic com/laiqian/pos/hardware/RootUrlParameter.clb : I
    //   161: ldc 'kng05w9ukms2wtlf'
    //   163: putstatic com/laiqian/pos/hardware/RootUrlParameter.clc : Ljava/lang/String;
    //   166: getstatic com/laiqian/pos/hardware/RootUrlParameter.ckN : Ljava/lang/String;
    //   169: putstatic com/laiqian/pos/hardware/RootUrlParameter.cld : Ljava/lang/String;
    //   172: ldc 'http://swoole.91laiqian.com/'
    //   174: putstatic com/laiqian/pos/hardware/RootUrlParameter.ckX : Ljava/lang/String;
    //   177: ldc 'http://file.91laiqian.com/'
    //   179: putstatic com/laiqian/pos/hardware/RootUrlParameter.clk : Ljava/lang/String;
    //   182: ldc 'http://news-system.91laiqian.com'
    //   184: putstatic com/laiqian/pos/hardware/RootUrlParameter.ckT : Ljava/lang/String;
    //   187: ldc 'http://news-system-nginx.91laiqian.com'
    //   189: putstatic com/laiqian/pos/hardware/RootUrlParameter.ckU : Ljava/lang/String;
    //   192: ldc 'http://91laiqian-apk.oss-cn-qingdao.aliyuncs.com/message_push_by_channel'
    //   194: putstatic com/laiqian/pos/hardware/RootUrlParameter.ckR : Ljava/lang/String;
    //   197: goto -> 1499
    //   200: ldc 'https://ta.91laiqian.com/'
    //   202: putstatic com/laiqian/pos/hardware/RootUrlParameter.ckV : Ljava/lang/String;
    //   205: ldc 'https://order.91laiqian.com/'
    //   207: putstatic com/laiqian/pos/hardware/RootUrlParameter.ckW : Ljava/lang/String;
    //   210: ldc 'http://hotpatch.jindou.info'
    //   212: putstatic com/laiqian/pos/hardware/RootUrlParameter.ckN : Ljava/lang/String;
    //   215: ldc 'http://91laiqian-cdn-image.oss-cn-qingdao.aliyuncs.com/'
    //   217: putstatic com/laiqian/pos/hardware/RootUrlParameter.cll : Ljava/lang/String;
    //   220: ldc 'http://wallet.jindou.info/'
    //   222: putstatic com/laiqian/pos/hardware/RootUrlParameter.ckS : Ljava/lang/String;
    //   225: ldc 'http://online.jindou.info/'
    //   227: putstatic com/laiqian/pos/hardware/RootUrlParameter.ckC : Ljava/lang/String;
    //   230: ldc 'http://open-table.91laiqian.com/'
    //   232: putstatic com/laiqian/pos/hardware/RootUrlParameter.ckD : Ljava/lang/String;
    //   235: ldc 'http://user.91laiqian.com'
    //   237: putstatic com/laiqian/pos/hardware/RootUrlParameter.ckI : Ljava/lang/String;
    //   240: ldc 'http://channel.jindou.info'
    //   242: putstatic com/laiqian/pos/hardware/RootUrlParameter.ckY : Ljava/lang/String;
    //   245: new java/lang/StringBuilder
    //   248: dup
    //   249: invokespecial <init> : ()V
    //   252: astore_3
    //   253: aload_3
    //   254: getstatic com/laiqian/pos/hardware/RootUrlParameter.ckC : Ljava/lang/String;
    //   257: invokevirtual append : (Ljava/lang/String;)Ljava/lang/StringBuilder;
    //   260: pop
    //   261: aload_3
    //   262: ldc 'transaction/index'
    //   264: invokevirtual append : (Ljava/lang/String;)Ljava/lang/StringBuilder;
    //   267: pop
    //   268: aload_3
    //   269: invokevirtual toString : ()Ljava/lang/String;
    //   272: putstatic com/laiqian/pos/hardware/RootUrlParameter.cla : Ljava/lang/String;
    //   275: ldc_w 'download.jindou.info'
    //   278: putstatic com/laiqian/pos/hardware/RootUrlParameter.ckZ : Ljava/lang/String;
    //   281: ldc 100114
    //   283: putstatic com/laiqian/pos/hardware/RootUrlParameter.clb : I
    //   286: ldc 'kng05w9ukms2wtlf'
    //   288: putstatic com/laiqian/pos/hardware/RootUrlParameter.clc : Ljava/lang/String;
    //   291: getstatic com/laiqian/pos/hardware/RootUrlParameter.ckN : Ljava/lang/String;
    //   294: putstatic com/laiqian/pos/hardware/RootUrlParameter.cld : Ljava/lang/String;
    //   297: ldc 'http://swoole.91laiqian.com/'
    //   299: putstatic com/laiqian/pos/hardware/RootUrlParameter.ckX : Ljava/lang/String;
    //   302: ldc 'http://file.91laiqian.com/'
    //   304: putstatic com/laiqian/pos/hardware/RootUrlParameter.clk : Ljava/lang/String;
    //   307: ldc 'http://news-system.91laiqian.com'
    //   309: putstatic com/laiqian/pos/hardware/RootUrlParameter.ckT : Ljava/lang/String;
    //   312: ldc 'http://news-system-nginx.91laiqian.com'
    //   314: putstatic com/laiqian/pos/hardware/RootUrlParameter.ckU : Ljava/lang/String;
    //   317: goto -> 1499
    //   320: ldc 'https://ta.91laiqian.com/'
    //   322: putstatic com/laiqian/pos/hardware/RootUrlParameter.ckV : Ljava/lang/String;
    //   325: ldc 'https://order.91laiqian.com/'
    //   327: putstatic com/laiqian/pos/hardware/RootUrlParameter.ckW : Ljava/lang/String;
    //   330: ldc 'http://hotpatch.jindou.info'
    //   332: putstatic com/laiqian/pos/hardware/RootUrlParameter.ckN : Ljava/lang/String;
    //   335: ldc 'http://91laiqian-cdn-image.oss-cn-qingdao.aliyuncs.com/'
    //   337: putstatic com/laiqian/pos/hardware/RootUrlParameter.cll : Ljava/lang/String;
    //   340: ldc 'http://wallet.jindou.info/'
    //   342: putstatic com/laiqian/pos/hardware/RootUrlParameter.ckS : Ljava/lang/String;
    //   345: ldc 'http://online.jindou.info/'
    //   347: putstatic com/laiqian/pos/hardware/RootUrlParameter.ckC : Ljava/lang/String;
    //   350: ldc 'http://open-table.91laiqian.com/'
    //   352: putstatic com/laiqian/pos/hardware/RootUrlParameter.ckD : Ljava/lang/String;
    //   355: ldc 'http://user.91laiqian.com'
    //   357: putstatic com/laiqian/pos/hardware/RootUrlParameter.ckI : Ljava/lang/String;
    //   360: ldc 'http://channel.jindou.info'
    //   362: putstatic com/laiqian/pos/hardware/RootUrlParameter.ckY : Ljava/lang/String;
    //   365: new java/lang/StringBuilder
    //   368: dup
    //   369: invokespecial <init> : ()V
    //   372: astore_3
    //   373: aload_3
    //   374: getstatic com/laiqian/pos/hardware/RootUrlParameter.ckC : Ljava/lang/String;
    //   377: invokevirtual append : (Ljava/lang/String;)Ljava/lang/StringBuilder;
    //   380: pop
    //   381: aload_3
    //   382: ldc 'transaction/index'
    //   384: invokevirtual append : (Ljava/lang/String;)Ljava/lang/StringBuilder;
    //   387: pop
    //   388: aload_3
    //   389: invokevirtual toString : ()Ljava/lang/String;
    //   392: putstatic com/laiqian/pos/hardware/RootUrlParameter.cla : Ljava/lang/String;
    //   395: ldc_w 'download.jindou.info'
    //   398: putstatic com/laiqian/pos/hardware/RootUrlParameter.ckZ : Ljava/lang/String;
    //   401: ldc 100114
    //   403: putstatic com/laiqian/pos/hardware/RootUrlParameter.clb : I
    //   406: ldc 'kng05w9ukms2wtlf'
    //   408: putstatic com/laiqian/pos/hardware/RootUrlParameter.clc : Ljava/lang/String;
    //   411: getstatic com/laiqian/pos/hardware/RootUrlParameter.ckN : Ljava/lang/String;
    //   414: putstatic com/laiqian/pos/hardware/RootUrlParameter.cld : Ljava/lang/String;
    //   417: ldc 'http://swoole.91laiqian.com/'
    //   419: putstatic com/laiqian/pos/hardware/RootUrlParameter.ckX : Ljava/lang/String;
    //   422: ldc 'http://file.91laiqian.com/'
    //   424: putstatic com/laiqian/pos/hardware/RootUrlParameter.clk : Ljava/lang/String;
    //   427: ldc 'http://news-system.91laiqian.com'
    //   429: putstatic com/laiqian/pos/hardware/RootUrlParameter.ckT : Ljava/lang/String;
    //   432: ldc 'http://news-system-nginx.91laiqian.com'
    //   434: putstatic com/laiqian/pos/hardware/RootUrlParameter.ckU : Ljava/lang/String;
    //   437: goto -> 1499
    //   440: ldc 'https://ta.91laiqian.com/'
    //   442: putstatic com/laiqian/pos/hardware/RootUrlParameter.ckV : Ljava/lang/String;
    //   445: ldc 'https://order.91laiqian.com/'
    //   447: putstatic com/laiqian/pos/hardware/RootUrlParameter.ckW : Ljava/lang/String;
    //   450: ldc 'http://hotpatch.jindou.info'
    //   452: putstatic com/laiqian/pos/hardware/RootUrlParameter.ckN : Ljava/lang/String;
    //   455: ldc 'http://91laiqian-cdn-image.oss-cn-qingdao.aliyuncs.com/'
    //   457: putstatic com/laiqian/pos/hardware/RootUrlParameter.cll : Ljava/lang/String;
    //   460: ldc 'http://wallet.jindou.info/'
    //   462: putstatic com/laiqian/pos/hardware/RootUrlParameter.ckS : Ljava/lang/String;
    //   465: ldc 'http://online.jindou.info/'
    //   467: putstatic com/laiqian/pos/hardware/RootUrlParameter.ckC : Ljava/lang/String;
    //   470: ldc 'http://open-table.91laiqian.com/'
    //   472: putstatic com/laiqian/pos/hardware/RootUrlParameter.ckD : Ljava/lang/String;
    //   475: ldc 'http://user.91laiqian.com'
    //   477: putstatic com/laiqian/pos/hardware/RootUrlParameter.ckI : Ljava/lang/String;
    //   480: ldc 'http://channel.jindou.info'
    //   482: putstatic com/laiqian/pos/hardware/RootUrlParameter.ckY : Ljava/lang/String;
    //   485: new java/lang/StringBuilder
    //   488: dup
    //   489: invokespecial <init> : ()V
    //   492: astore_3
    //   493: aload_3
    //   494: getstatic com/laiqian/pos/hardware/RootUrlParameter.ckC : Ljava/lang/String;
    //   497: invokevirtual append : (Ljava/lang/String;)Ljava/lang/StringBuilder;
    //   500: pop
    //   501: aload_3
    //   502: ldc 'transaction/index'
    //   504: invokevirtual append : (Ljava/lang/String;)Ljava/lang/StringBuilder;
    //   507: pop
    //   508: aload_3
    //   509: invokevirtual toString : ()Ljava/lang/String;
    //   512: putstatic com/laiqian/pos/hardware/RootUrlParameter.cla : Ljava/lang/String;
    //   515: ldc_w 'download.jindou.info'
    //   518: putstatic com/laiqian/pos/hardware/RootUrlParameter.ckZ : Ljava/lang/String;
    //   521: ldc 100114
    //   523: putstatic com/laiqian/pos/hardware/RootUrlParameter.clb : I
    //   526: ldc 'kng05w9ukms2wtlf'
    //   528: putstatic com/laiqian/pos/hardware/RootUrlParameter.clc : Ljava/lang/String;
    //   531: getstatic com/laiqian/pos/hardware/RootUrlParameter.ckN : Ljava/lang/String;
    //   534: putstatic com/laiqian/pos/hardware/RootUrlParameter.cld : Ljava/lang/String;
    //   537: ldc 'http://swoole.91laiqian.com/'
    //   539: putstatic com/laiqian/pos/hardware/RootUrlParameter.ckX : Ljava/lang/String;
    //   542: ldc 'http://file.91laiqian.com/'
    //   544: putstatic com/laiqian/pos/hardware/RootUrlParameter.clk : Ljava/lang/String;
    //   547: ldc 'http://news-system.91laiqian.com'
    //   549: putstatic com/laiqian/pos/hardware/RootUrlParameter.ckT : Ljava/lang/String;
    //   552: ldc 'http://news-system-nginx.91laiqian.com'
    //   554: putstatic com/laiqian/pos/hardware/RootUrlParameter.ckU : Ljava/lang/String;
    //   557: ldc 'http://91laiqian-apk.oss-cn-qingdao.aliyuncs.com/message_push_by_channel'
    //   559: putstatic com/laiqian/pos/hardware/RootUrlParameter.ckR : Ljava/lang/String;
    //   562: goto -> 1499
    //   565: ldc_w 'interface.91laiqian.com'
    //   568: putstatic com/laiqian/pos/hardware/RootUrlParameter.ckJ : Ljava/lang/String;
    //   571: ldc 'https://ta.91laiqian.com/'
    //   573: putstatic com/laiqian/pos/hardware/RootUrlParameter.ckV : Ljava/lang/String;
    //   576: ldc 'https://order.91laiqian.com/'
    //   578: putstatic com/laiqian/pos/hardware/RootUrlParameter.ckW : Ljava/lang/String;
    //   581: ldc_w 'http://wallet.91laiqian.com/'
    //   584: putstatic com/laiqian/pos/hardware/RootUrlParameter.ckS : Ljava/lang/String;
    //   587: ldc 'http://channel.91laiqian.com'
    //   589: putstatic com/laiqian/pos/hardware/RootUrlParameter.ckY : Ljava/lang/String;
    //   592: ldc_w 'download.androidcloudpos.cn'
    //   595: putstatic com/laiqian/pos/hardware/RootUrlParameter.ckZ : Ljava/lang/String;
    //   598: ldc 'http://online.91laiqian.com/transaction/index'
    //   600: putstatic com/laiqian/pos/hardware/RootUrlParameter.cla : Ljava/lang/String;
    //   603: ldc 'http://online.91laiqian.com/'
    //   605: putstatic com/laiqian/pos/hardware/RootUrlParameter.ckC : Ljava/lang/String;
    //   608: ldc 'http://open-table.91laiqian.com/'
    //   610: putstatic com/laiqian/pos/hardware/RootUrlParameter.ckD : Ljava/lang/String;
    //   613: ldc 'http://user.91laiqian.com'
    //   615: putstatic com/laiqian/pos/hardware/RootUrlParameter.ckI : Ljava/lang/String;
    //   618: ldc_w 'http://hotpatch.91laiqian.com'
    //   621: putstatic com/laiqian/pos/hardware/RootUrlParameter.ckN : Ljava/lang/String;
    //   624: ldc 'http://91laiqian-cdn-image.oss-cn-qingdao.aliyuncs.com/'
    //   626: putstatic com/laiqian/pos/hardware/RootUrlParameter.cll : Ljava/lang/String;
    //   629: ldc 100114
    //   631: putstatic com/laiqian/pos/hardware/RootUrlParameter.clb : I
    //   634: ldc 'kng05w9ukms2wtlf'
    //   636: putstatic com/laiqian/pos/hardware/RootUrlParameter.clc : Ljava/lang/String;
    //   639: getstatic com/laiqian/pos/hardware/RootUrlParameter.ckN : Ljava/lang/String;
    //   642: putstatic com/laiqian/pos/hardware/RootUrlParameter.cld : Ljava/lang/String;
    //   645: ldc 'http://swoole.91laiqian.com/'
    //   647: putstatic com/laiqian/pos/hardware/RootUrlParameter.ckX : Ljava/lang/String;
    //   650: ldc 'http://file.91laiqian.com/'
    //   652: putstatic com/laiqian/pos/hardware/RootUrlParameter.clk : Ljava/lang/String;
    //   655: ldc 'http://news-system.91laiqian.com'
    //   657: putstatic com/laiqian/pos/hardware/RootUrlParameter.ckT : Ljava/lang/String;
    //   660: ldc 'http://news-system-nginx.91laiqian.com'
    //   662: putstatic com/laiqian/pos/hardware/RootUrlParameter.ckU : Ljava/lang/String;
    //   665: ldc 'http://91laiqian-apk.oss-cn-qingdao.aliyuncs.com/message_push_by_channel'
    //   667: putstatic com/laiqian/pos/hardware/RootUrlParameter.ckR : Ljava/lang/String;
    //   670: goto -> 1499
    //   673: ldc 'http://hotpatch.jindou.info'
    //   675: putstatic com/laiqian/pos/hardware/RootUrlParameter.ckN : Ljava/lang/String;
    //   678: ldc 'http://91laiqian-cdn-image.oss-cn-qingdao.aliyuncs.com/'
    //   680: putstatic com/laiqian/pos/hardware/RootUrlParameter.cll : Ljava/lang/String;
    //   683: ldc 'http://wallet.jindou.info/'
    //   685: putstatic com/laiqian/pos/hardware/RootUrlParameter.ckS : Ljava/lang/String;
    //   688: ldc 'http://online.jindou.info/'
    //   690: putstatic com/laiqian/pos/hardware/RootUrlParameter.ckC : Ljava/lang/String;
    //   693: ldc 'http://open-table.91laiqian.com/'
    //   695: putstatic com/laiqian/pos/hardware/RootUrlParameter.ckD : Ljava/lang/String;
    //   698: ldc 'http://user.91laiqian.com'
    //   700: putstatic com/laiqian/pos/hardware/RootUrlParameter.ckI : Ljava/lang/String;
    //   703: ldc 'http://channel.jindou.info'
    //   705: putstatic com/laiqian/pos/hardware/RootUrlParameter.ckY : Ljava/lang/String;
    //   708: new java/lang/StringBuilder
    //   711: dup
    //   712: invokespecial <init> : ()V
    //   715: astore_3
    //   716: aload_3
    //   717: getstatic com/laiqian/pos/hardware/RootUrlParameter.ckC : Ljava/lang/String;
    //   720: invokevirtual append : (Ljava/lang/String;)Ljava/lang/StringBuilder;
    //   723: pop
    //   724: aload_3
    //   725: ldc 'transaction/index'
    //   727: invokevirtual append : (Ljava/lang/String;)Ljava/lang/StringBuilder;
    //   730: pop
    //   731: aload_3
    //   732: invokevirtual toString : ()Ljava/lang/String;
    //   735: putstatic com/laiqian/pos/hardware/RootUrlParameter.cla : Ljava/lang/String;
    //   738: ldc_w 'download.jindou.info'
    //   741: putstatic com/laiqian/pos/hardware/RootUrlParameter.ckZ : Ljava/lang/String;
    //   744: ldc 'https://ta.91laiqian.com/'
    //   746: putstatic com/laiqian/pos/hardware/RootUrlParameter.ckV : Ljava/lang/String;
    //   749: ldc 'https://order.91laiqian.com/'
    //   751: putstatic com/laiqian/pos/hardware/RootUrlParameter.ckW : Ljava/lang/String;
    //   754: ldc 100114
    //   756: putstatic com/laiqian/pos/hardware/RootUrlParameter.clb : I
    //   759: ldc 'kng05w9ukms2wtlf'
    //   761: putstatic com/laiqian/pos/hardware/RootUrlParameter.clc : Ljava/lang/String;
    //   764: getstatic com/laiqian/pos/hardware/RootUrlParameter.ckN : Ljava/lang/String;
    //   767: putstatic com/laiqian/pos/hardware/RootUrlParameter.cld : Ljava/lang/String;
    //   770: ldc 'http://swoole.91laiqian.com/'
    //   772: putstatic com/laiqian/pos/hardware/RootUrlParameter.ckX : Ljava/lang/String;
    //   775: ldc 'http://file.91laiqian.com/'
    //   777: putstatic com/laiqian/pos/hardware/RootUrlParameter.clk : Ljava/lang/String;
    //   780: ldc 'http://news-system.91laiqian.com'
    //   782: putstatic com/laiqian/pos/hardware/RootUrlParameter.ckT : Ljava/lang/String;
    //   785: ldc 'http://news-system-nginx.91laiqian.com'
    //   787: putstatic com/laiqian/pos/hardware/RootUrlParameter.ckU : Ljava/lang/String;
    //   790: ldc 'http://91laiqian-apk.oss-cn-qingdao.aliyuncs.com/message_push_by_channel'
    //   792: putstatic com/laiqian/pos/hardware/RootUrlParameter.ckR : Ljava/lang/String;
    //   795: goto -> 1499
    //   798: ldc_w 'singapore.91laiqian.com'
    //   801: putstatic com/laiqian/pos/hardware/RootUrlParameter.ckJ : Ljava/lang/String;
    //   804: ldc_w 'http://91laiqian-singapore-cdn-image.oss-ap-southeast-1.aliyuncs.com/'
    //   807: putstatic com/laiqian/pos/hardware/RootUrlParameter.cll : Ljava/lang/String;
    //   810: getstatic com/laiqian/pos/hardware/RootUrlParameter.ckO : Ljava/lang/String;
    //   813: putstatic com/laiqian/pos/hardware/RootUrlParameter.ckN : Ljava/lang/String;
    //   816: ldc_w 'http://wallet-singapore.91laiqian.com/'
    //   819: putstatic com/laiqian/pos/hardware/RootUrlParameter.ckS : Ljava/lang/String;
    //   822: ldc_w 'http://interface.cashcow.im/'
    //   825: putstatic com/laiqian/pos/hardware/RootUrlParameter.ckC : Ljava/lang/String;
    //   828: ldc 'http://open-table.91laiqian.com/'
    //   830: putstatic com/laiqian/pos/hardware/RootUrlParameter.ckD : Ljava/lang/String;
    //   833: ldc 'http://user.91laiqian.com'
    //   835: putstatic com/laiqian/pos/hardware/RootUrlParameter.ckI : Ljava/lang/String;
    //   838: ldc_w 'http://channel.evako.asia/'
    //   841: putstatic com/laiqian/pos/hardware/RootUrlParameter.ckY : Ljava/lang/String;
    //   844: ldc_w 'http://takeout.orderway.ca/'
    //   847: putstatic com/laiqian/pos/hardware/RootUrlParameter.ckV : Ljava/lang/String;
    //   850: getstatic com/laiqian/pos/hardware/RootUrlParameter.ckV : Ljava/lang/String;
    //   853: putstatic com/laiqian/pos/hardware/RootUrlParameter.ckW : Ljava/lang/String;
    //   856: ldc_w 'download-singapore.cashcow.im'
    //   859: putstatic com/laiqian/pos/hardware/RootUrlParameter.ckZ : Ljava/lang/String;
    //   862: ldc_w 'http://interface.cashcow.im/transaction/index'
    //   865: putstatic com/laiqian/pos/hardware/RootUrlParameter.cla : Ljava/lang/String;
    //   868: ldc 100114
    //   870: putstatic com/laiqian/pos/hardware/RootUrlParameter.clb : I
    //   873: ldc 'kng05w9ukms2wtlf'
    //   875: putstatic com/laiqian/pos/hardware/RootUrlParameter.clc : Ljava/lang/String;
    //   878: getstatic com/laiqian/pos/hardware/RootUrlParameter.ckN : Ljava/lang/String;
    //   881: putstatic com/laiqian/pos/hardware/RootUrlParameter.cld : Ljava/lang/String;
    //   884: ldc 'http://swoole.91laiqian.com/'
    //   886: putstatic com/laiqian/pos/hardware/RootUrlParameter.ckX : Ljava/lang/String;
    //   889: ldc 'http://file.91laiqian.com/'
    //   891: putstatic com/laiqian/pos/hardware/RootUrlParameter.clk : Ljava/lang/String;
    //   894: ldc_w 'http://abroad-news-system.91laiqian.com'
    //   897: putstatic com/laiqian/pos/hardware/RootUrlParameter.ckT : Ljava/lang/String;
    //   900: ldc_w 'http://abroad-news-system-nginx.91laiqian.com'
    //   903: putstatic com/laiqian/pos/hardware/RootUrlParameter.ckU : Ljava/lang/String;
    //   906: ldc_w 'http://91laiqian-singapore-cdn-image.oss-ap-southeast-1.aliyuncs.com/message_push_by_channel'
    //   909: putstatic com/laiqian/pos/hardware/RootUrlParameter.ckR : Ljava/lang/String;
    //   912: goto -> 1499
    //   915: ldc 'https://ta.91laiqian.com/'
    //   917: putstatic com/laiqian/pos/hardware/RootUrlParameter.ckV : Ljava/lang/String;
    //   920: ldc 'https://order.91laiqian.com/'
    //   922: putstatic com/laiqian/pos/hardware/RootUrlParameter.ckW : Ljava/lang/String;
    //   925: ldc_w 'http://hotpatch.androidcloudpos.cn'
    //   928: putstatic com/laiqian/pos/hardware/RootUrlParameter.ckN : Ljava/lang/String;
    //   931: ldc 'http://91laiqian-cdn-image.oss-cn-qingdao.aliyuncs.com/'
    //   933: putstatic com/laiqian/pos/hardware/RootUrlParameter.cll : Ljava/lang/String;
    //   936: ldc_w 'http://wallet.androidcloudpos.cn/'
    //   939: putstatic com/laiqian/pos/hardware/RootUrlParameter.ckS : Ljava/lang/String;
    //   942: ldc_w 'http://online.androidcloudpos.cn/'
    //   945: putstatic com/laiqian/pos/hardware/RootUrlParameter.ckC : Ljava/lang/String;
    //   948: ldc 'http://open-table.91laiqian.com/'
    //   950: putstatic com/laiqian/pos/hardware/RootUrlParameter.ckD : Ljava/lang/String;
    //   953: ldc 'http://user.91laiqian.com'
    //   955: putstatic com/laiqian/pos/hardware/RootUrlParameter.ckI : Ljava/lang/String;
    //   958: ldc_w 'http://channel.androidcloudpos.cn'
    //   961: putstatic com/laiqian/pos/hardware/RootUrlParameter.ckY : Ljava/lang/String;
    //   964: ldc_w 'download.androidcloudpos.cn'
    //   967: putstatic com/laiqian/pos/hardware/RootUrlParameter.ckZ : Ljava/lang/String;
    //   970: new java/lang/StringBuilder
    //   973: dup
    //   974: invokespecial <init> : ()V
    //   977: astore_3
    //   978: aload_3
    //   979: getstatic com/laiqian/pos/hardware/RootUrlParameter.ckC : Ljava/lang/String;
    //   982: invokevirtual append : (Ljava/lang/String;)Ljava/lang/StringBuilder;
    //   985: pop
    //   986: aload_3
    //   987: ldc 'transaction/index'
    //   989: invokevirtual append : (Ljava/lang/String;)Ljava/lang/StringBuilder;
    //   992: pop
    //   993: aload_3
    //   994: invokevirtual toString : ()Ljava/lang/String;
    //   997: putstatic com/laiqian/pos/hardware/RootUrlParameter.cla : Ljava/lang/String;
    //   1000: ldc 100114
    //   1002: putstatic com/laiqian/pos/hardware/RootUrlParameter.clb : I
    //   1005: ldc 'kng05w9ukms2wtlf'
    //   1007: putstatic com/laiqian/pos/hardware/RootUrlParameter.clc : Ljava/lang/String;
    //   1010: getstatic com/laiqian/pos/hardware/RootUrlParameter.ckN : Ljava/lang/String;
    //   1013: putstatic com/laiqian/pos/hardware/RootUrlParameter.cld : Ljava/lang/String;
    //   1016: ldc 'http://swoole.91laiqian.com/'
    //   1018: putstatic com/laiqian/pos/hardware/RootUrlParameter.ckX : Ljava/lang/String;
    //   1021: ldc 'http://file.91laiqian.com/'
    //   1023: putstatic com/laiqian/pos/hardware/RootUrlParameter.clk : Ljava/lang/String;
    //   1026: ldc 'http://news-system.91laiqian.com'
    //   1028: putstatic com/laiqian/pos/hardware/RootUrlParameter.ckT : Ljava/lang/String;
    //   1031: ldc 'http://news-system-nginx.91laiqian.com'
    //   1033: putstatic com/laiqian/pos/hardware/RootUrlParameter.ckU : Ljava/lang/String;
    //   1036: ldc 'http://91laiqian-apk.oss-cn-qingdao.aliyuncs.com/message_push_by_channel'
    //   1038: putstatic com/laiqian/pos/hardware/RootUrlParameter.ckR : Ljava/lang/String;
    //   1041: goto -> 1499
    //   1044: getstatic com/laiqian/pos/hardware/RootUrlParameter.ckP : Ljava/lang/String;
    //   1047: putstatic com/laiqian/pos/hardware/RootUrlParameter.ckN : Ljava/lang/String;
    //   1050: ldc_w 'https://pos-pre-wallet-hch.91laiqian.com/'
    //   1053: putstatic com/laiqian/pos/hardware/RootUrlParameter.ckV : Ljava/lang/String;
    //   1056: ldc_w 'https://pos-pre-wallet-hch.91laiqian.com/'
    //   1059: putstatic com/laiqian/pos/hardware/RootUrlParameter.ckW : Ljava/lang/String;
    //   1062: ldc 'http://91laiqian-cdn-image.oss-cn-qingdao.aliyuncs.com/'
    //   1064: putstatic com/laiqian/pos/hardware/RootUrlParameter.cll : Ljava/lang/String;
    //   1067: ldc_w 'http://pos-pre-wallet.91laiqian.com/'
    //   1070: putstatic com/laiqian/pos/hardware/RootUrlParameter.ckS : Ljava/lang/String;
    //   1073: ldc_w 'http://pos-pre-interface.91laiqian.com/'
    //   1076: putstatic com/laiqian/pos/hardware/RootUrlParameter.ckC : Ljava/lang/String;
    //   1079: ldc_w 'http://pre-open-table.91laiqian.com/'
    //   1082: putstatic com/laiqian/pos/hardware/RootUrlParameter.ckD : Ljava/lang/String;
    //   1085: ldc_w 'http://pre-user.91laiqian.com'
    //   1088: putstatic com/laiqian/pos/hardware/RootUrlParameter.ckI : Ljava/lang/String;
    //   1091: ldc_w 'http://pos-pre-channel.91laiqian.com'
    //   1094: putstatic com/laiqian/pos/hardware/RootUrlParameter.ckY : Ljava/lang/String;
    //   1097: ldc_w 'pre-download.91laiqian.com'
    //   1100: putstatic com/laiqian/pos/hardware/RootUrlParameter.ckZ : Ljava/lang/String;
    //   1103: ldc_w 'http://pos-pre-interface.91laiqian.com/transaction/index'
    //   1106: putstatic com/laiqian/pos/hardware/RootUrlParameter.cla : Ljava/lang/String;
    //   1109: ldc_w 100571
    //   1112: putstatic com/laiqian/pos/hardware/RootUrlParameter.clb : I
    //   1115: ldc_w 'vgruypn2h2c61syk'
    //   1118: putstatic com/laiqian/pos/hardware/RootUrlParameter.clc : Ljava/lang/String;
    //   1121: getstatic com/laiqian/pos/hardware/RootUrlParameter.ckN : Ljava/lang/String;
    //   1124: putstatic com/laiqian/pos/hardware/RootUrlParameter.cld : Ljava/lang/String;
    //   1127: ldc_w 'http://swoole-pre.91laiqian.com/'
    //   1130: putstatic com/laiqian/pos/hardware/RootUrlParameter.ckX : Ljava/lang/String;
    //   1133: ldc 'http://pre-file.91laiqian.com/'
    //   1135: putstatic com/laiqian/pos/hardware/RootUrlParameter.clk : Ljava/lang/String;
    //   1138: ldc_w 'http://pre-news-system.91laiqian.com'
    //   1141: putstatic com/laiqian/pos/hardware/RootUrlParameter.ckT : Ljava/lang/String;
    //   1144: ldc_w 'http://pre-news-system-nginx.91laiqian.com'
    //   1147: putstatic com/laiqian/pos/hardware/RootUrlParameter.ckU : Ljava/lang/String;
    //   1150: ldc_w 'http://91laiqian-singapore-cdn-image.oss-ap-southeast-1.aliyuncs.com/message_push_by_channel'
    //   1153: putstatic com/laiqian/pos/hardware/RootUrlParameter.ckR : Ljava/lang/String;
    //   1156: goto -> 1499
    //   1159: getstatic com/laiqian/pos/hardware/RootUrlParameter.ckO : Ljava/lang/String;
    //   1162: putstatic com/laiqian/pos/hardware/RootUrlParameter.ckN : Ljava/lang/String;
    //   1165: ldc_w 'http://order-singapore.91laiqian.com/'
    //   1168: putstatic com/laiqian/pos/hardware/RootUrlParameter.ckV : Ljava/lang/String;
    //   1171: ldc_w 'http://order-singapore.91laiqian.com/'
    //   1174: putstatic com/laiqian/pos/hardware/RootUrlParameter.ckW : Ljava/lang/String;
    //   1177: ldc_w 'http://91laiqian-singapore-cdn-image.oss-ap-southeast-1.aliyuncs.com/'
    //   1180: putstatic com/laiqian/pos/hardware/RootUrlParameter.cll : Ljava/lang/String;
    //   1183: ldc_w 'http://wallet-singapore.91laiqian.com/'
    //   1186: putstatic com/laiqian/pos/hardware/RootUrlParameter.ckS : Ljava/lang/String;
    //   1189: ldc_w 'http://interface.cashcow.im/'
    //   1192: putstatic com/laiqian/pos/hardware/RootUrlParameter.ckC : Ljava/lang/String;
    //   1195: ldc_w 'http://open-table-singapore.91laiqian.com/'
    //   1198: putstatic com/laiqian/pos/hardware/RootUrlParameter.ckD : Ljava/lang/String;
    //   1201: ldc_w 'http://user.cashcow.im'
    //   1204: putstatic com/laiqian/pos/hardware/RootUrlParameter.ckI : Ljava/lang/String;
    //   1207: ldc_w 'http://channel.evako.asia/'
    //   1210: putstatic com/laiqian/pos/hardware/RootUrlParameter.ckY : Ljava/lang/String;
    //   1213: ldc_w 'download-singapore.cashcow.im'
    //   1216: putstatic com/laiqian/pos/hardware/RootUrlParameter.ckZ : Ljava/lang/String;
    //   1219: ldc_w 'http://interface.cashcow.im/transaction/index'
    //   1222: putstatic com/laiqian/pos/hardware/RootUrlParameter.cla : Ljava/lang/String;
    //   1225: ldc 100114
    //   1227: putstatic com/laiqian/pos/hardware/RootUrlParameter.clb : I
    //   1230: ldc 'kng05w9ukms2wtlf'
    //   1232: putstatic com/laiqian/pos/hardware/RootUrlParameter.clc : Ljava/lang/String;
    //   1235: getstatic com/laiqian/pos/hardware/RootUrlParameter.ckN : Ljava/lang/String;
    //   1238: putstatic com/laiqian/pos/hardware/RootUrlParameter.cld : Ljava/lang/String;
    //   1241: ldc_w 'http://swoole-singapore.91laiqian.com/'
    //   1244: putstatic com/laiqian/pos/hardware/RootUrlParameter.ckX : Ljava/lang/String;
    //   1247: ldc 'http://file.91laiqian.com/'
    //   1249: putstatic com/laiqian/pos/hardware/RootUrlParameter.clk : Ljava/lang/String;
    //   1252: ldc_w 'http://abroad-news-system.91laiqian.com'
    //   1255: putstatic com/laiqian/pos/hardware/RootUrlParameter.ckT : Ljava/lang/String;
    //   1258: ldc_w 'http://abroad-news-system-nginx.91laiqian.com'
    //   1261: putstatic com/laiqian/pos/hardware/RootUrlParameter.ckU : Ljava/lang/String;
    //   1264: ldc_w 'http://91laiqian-singapore-cdn-image.oss-ap-southeast-1.aliyuncs.com/message_push_by_channel'
    //   1267: putstatic com/laiqian/pos/hardware/RootUrlParameter.ckR : Ljava/lang/String;
    //   1270: goto -> 1499
    //   1273: ldc_w 'http://91laiqian-singapore-cdn-image.oss-ap-southeast-1.aliyuncs.com/'
    //   1276: putstatic com/laiqian/pos/hardware/RootUrlParameter.cll : Ljava/lang/String;
    //   1279: getstatic com/laiqian/pos/hardware/RootUrlParameter.ckO : Ljava/lang/String;
    //   1282: putstatic com/laiqian/pos/hardware/RootUrlParameter.ckN : Ljava/lang/String;
    //   1285: ldc_w 'http://wallet-singapore.91laiqian.com/'
    //   1288: putstatic com/laiqian/pos/hardware/RootUrlParameter.ckS : Ljava/lang/String;
    //   1291: ldc_w 'http://interface.cashcow.im/'
    //   1294: putstatic com/laiqian/pos/hardware/RootUrlParameter.ckC : Ljava/lang/String;
    //   1297: ldc_w 'http://open-table-singapore.91laiqian.com/'
    //   1300: putstatic com/laiqian/pos/hardware/RootUrlParameter.ckD : Ljava/lang/String;
    //   1303: ldc_w 'http://user.cashcow.im'
    //   1306: putstatic com/laiqian/pos/hardware/RootUrlParameter.ckI : Ljava/lang/String;
    //   1309: ldc_w 'http://channel.evako.asia/'
    //   1312: putstatic com/laiqian/pos/hardware/RootUrlParameter.ckY : Ljava/lang/String;
    //   1315: ldc_w 'download-singapore.cashcow.im'
    //   1318: putstatic com/laiqian/pos/hardware/RootUrlParameter.ckZ : Ljava/lang/String;
    //   1321: ldc_w 'http://interface.cashcow.im/transaction/index'
    //   1324: putstatic com/laiqian/pos/hardware/RootUrlParameter.cla : Ljava/lang/String;
    //   1327: ldc_w 'http://order-singapore.91laiqian.com/'
    //   1330: putstatic com/laiqian/pos/hardware/RootUrlParameter.ckV : Ljava/lang/String;
    //   1333: ldc_w 'http://order-singapore.91laiqian.com/'
    //   1336: putstatic com/laiqian/pos/hardware/RootUrlParameter.ckW : Ljava/lang/String;
    //   1339: ldc 100114
    //   1341: putstatic com/laiqian/pos/hardware/RootUrlParameter.clb : I
    //   1344: ldc 'kng05w9ukms2wtlf'
    //   1346: putstatic com/laiqian/pos/hardware/RootUrlParameter.clc : Ljava/lang/String;
    //   1349: getstatic com/laiqian/pos/hardware/RootUrlParameter.ckN : Ljava/lang/String;
    //   1352: putstatic com/laiqian/pos/hardware/RootUrlParameter.cld : Ljava/lang/String;
    //   1355: ldc_w 'http://swoole-singapore.91laiqian.com/'
    //   1358: putstatic com/laiqian/pos/hardware/RootUrlParameter.ckX : Ljava/lang/String;
    //   1361: ldc_w 'http://file.cashcow.im/'
    //   1364: putstatic com/laiqian/pos/hardware/RootUrlParameter.clk : Ljava/lang/String;
    //   1367: ldc_w 'http://abroad-news-system.91laiqian.com'
    //   1370: putstatic com/laiqian/pos/hardware/RootUrlParameter.ckT : Ljava/lang/String;
    //   1373: ldc_w 'http://abroad-news-system-nginx.91laiqian.com'
    //   1376: putstatic com/laiqian/pos/hardware/RootUrlParameter.ckU : Ljava/lang/String;
    //   1379: ldc_w 'http://91laiqian-singapore-cdn-image.oss-ap-southeast-1.aliyuncs.com/message_push_by_channel'
    //   1382: putstatic com/laiqian/pos/hardware/RootUrlParameter.ckR : Ljava/lang/String;
    //   1385: goto -> 1499
    //   1388: getstatic com/laiqian/pos/hardware/RootUrlParameter.ckP : Ljava/lang/String;
    //   1391: putstatic com/laiqian/pos/hardware/RootUrlParameter.ckN : Ljava/lang/String;
    //   1394: ldc 'http://91laiqian-cdn-image.oss-cn-qingdao.aliyuncs.com/'
    //   1396: putstatic com/laiqian/pos/hardware/RootUrlParameter.cll : Ljava/lang/String;
    //   1399: ldc_w 'http://pos-pre-interface.91laiqian.com/'
    //   1402: putstatic com/laiqian/pos/hardware/RootUrlParameter.ckC : Ljava/lang/String;
    //   1405: ldc_w 'http://pre-open-table.91laiqian.com/'
    //   1408: putstatic com/laiqian/pos/hardware/RootUrlParameter.ckD : Ljava/lang/String;
    //   1411: ldc_w 'http://pre-user.91laiqian.com'
    //   1414: putstatic com/laiqian/pos/hardware/RootUrlParameter.ckI : Ljava/lang/String;
    //   1417: ldc_w 'http://pos-pre-wallet.91laiqian.com/'
    //   1420: putstatic com/laiqian/pos/hardware/RootUrlParameter.ckS : Ljava/lang/String;
    //   1423: ldc_w 'http://pos-pre-channel.91laiqian.com'
    //   1426: putstatic com/laiqian/pos/hardware/RootUrlParameter.ckY : Ljava/lang/String;
    //   1429: ldc_w 'https://pos-pre-wallet-hch.91laiqian.com/'
    //   1432: putstatic com/laiqian/pos/hardware/RootUrlParameter.ckV : Ljava/lang/String;
    //   1435: ldc_w 'https://pos-pre-wallet-hch.91laiqian.com/'
    //   1438: putstatic com/laiqian/pos/hardware/RootUrlParameter.ckW : Ljava/lang/String;
    //   1441: ldc_w 'pre-download.91laiqian.com'
    //   1444: putstatic com/laiqian/pos/hardware/RootUrlParameter.ckZ : Ljava/lang/String;
    //   1447: ldc_w 'http://pos-pre-interface.91laiqian.com/transaction/index'
    //   1450: putstatic com/laiqian/pos/hardware/RootUrlParameter.cla : Ljava/lang/String;
    //   1453: ldc_w 100571
    //   1456: putstatic com/laiqian/pos/hardware/RootUrlParameter.clb : I
    //   1459: ldc_w 'vgruypn2h2c61syk'
    //   1462: putstatic com/laiqian/pos/hardware/RootUrlParameter.clc : Ljava/lang/String;
    //   1465: getstatic com/laiqian/pos/hardware/RootUrlParameter.ckN : Ljava/lang/String;
    //   1468: putstatic com/laiqian/pos/hardware/RootUrlParameter.cld : Ljava/lang/String;
    //   1471: ldc_w 'http://swoole-pre.91laiqian.com/'
    //   1474: putstatic com/laiqian/pos/hardware/RootUrlParameter.ckX : Ljava/lang/String;
    //   1477: ldc 'http://pre-file.91laiqian.com/'
    //   1479: putstatic com/laiqian/pos/hardware/RootUrlParameter.clk : Ljava/lang/String;
    //   1482: ldc_w 'http://pre-news-system.91laiqian.com'
    //   1485: putstatic com/laiqian/pos/hardware/RootUrlParameter.ckT : Ljava/lang/String;
    //   1488: ldc_w 'http://pre-news-system-nginx.91laiqian.com'
    //   1491: putstatic com/laiqian/pos/hardware/RootUrlParameter.ckU : Ljava/lang/String;
    //   1494: ldc 'http://91laiqian-apk.oss-cn-qingdao.aliyuncs.com/message_push_by_channel'
    //   1496: putstatic com/laiqian/pos/hardware/RootUrlParameter.ckR : Ljava/lang/String;
    //   1499: new java/lang/StringBuilder
    //   1502: dup
    //   1503: invokespecial <init> : ()V
    //   1506: astore_3
    //   1507: aload_3
    //   1508: getstatic com/laiqian/pos/hardware/RootUrlParameter.ckI : Ljava/lang/String;
    //   1511: invokevirtual append : (Ljava/lang/String;)Ljava/lang/StringBuilder;
    //   1514: pop
    //   1515: aload_3
    //   1516: ldc_w '/lqkinterface/employee/delete/'
    //   1519: invokevirtual append : (Ljava/lang/String;)Ljava/lang/StringBuilder;
    //   1522: pop
    //   1523: aload_3
    //   1524: invokevirtual toString : ()Ljava/lang/String;
    //   1527: putstatic com/laiqian/pos/hardware/RootUrlParameter.ckB : Ljava/lang/String;
    //   1530: new java/lang/StringBuilder
    //   1533: dup
    //   1534: invokespecial <init> : ()V
    //   1537: astore_3
    //   1538: aload_3
    //   1539: getstatic com/laiqian/pos/hardware/RootUrlParameter.ckC : Ljava/lang/String;
    //   1542: invokevirtual append : (Ljava/lang/String;)Ljava/lang/StringBuilder;
    //   1545: pop
    //   1546: aload_3
    //   1547: ldc_w 'bpartner/memberinfo'
    //   1550: invokevirtual append : (Ljava/lang/String;)Ljava/lang/StringBuilder;
    //   1553: pop
    //   1554: aload_3
    //   1555: invokevirtual toString : ()Ljava/lang/String;
    //   1558: putstatic com/laiqian/pos/hardware/RootUrlParameter.ckE : Ljava/lang/String;
    //   1561: new java/lang/StringBuilder
    //   1564: dup
    //   1565: invokespecial <init> : ()V
    //   1568: astore_3
    //   1569: aload_3
    //   1570: getstatic com/laiqian/pos/hardware/RootUrlParameter.ckC : Ljava/lang/String;
    //   1573: invokevirtual append : (Ljava/lang/String;)Ljava/lang/StringBuilder;
    //   1576: pop
    //   1577: aload_3
    //   1578: ldc_w 'bpartner/chargedoclist'
    //   1581: invokevirtual append : (Ljava/lang/String;)Ljava/lang/StringBuilder;
    //   1584: pop
    //   1585: aload_3
    //   1586: invokevirtual toString : ()Ljava/lang/String;
    //   1589: putstatic com/laiqian/pos/hardware/RootUrlParameter.ckG : Ljava/lang/String;
    //   1592: new java/lang/StringBuilder
    //   1595: dup
    //   1596: invokespecial <init> : ()V
    //   1599: astore_3
    //   1600: aload_3
    //   1601: getstatic com/laiqian/pos/hardware/RootUrlParameter.ckC : Ljava/lang/String;
    //   1604: invokevirtual append : (Ljava/lang/String;)Ljava/lang/StringBuilder;
    //   1607: pop
    //   1608: aload_3
    //   1609: ldc_w 'bpartner/can-cancel'
    //   1612: invokevirtual append : (Ljava/lang/String;)Ljava/lang/StringBuilder;
    //   1615: pop
    //   1616: aload_3
    //   1617: invokevirtual toString : ()Ljava/lang/String;
    //   1620: putstatic com/laiqian/pos/hardware/RootUrlParameter.ckF : Ljava/lang/String;
    //   1623: new java/lang/StringBuilder
    //   1626: dup
    //   1627: invokespecial <init> : ()V
    //   1630: astore_3
    //   1631: aload_3
    //   1632: getstatic com/laiqian/pos/hardware/RootUrlParameter.cld : Ljava/lang/String;
    //   1635: invokevirtual append : (Ljava/lang/String;)Ljava/lang/StringBuilder;
    //   1638: pop
    //   1639: aload_3
    //   1640: ldc_w '/version/info'
    //   1643: invokevirtual append : (Ljava/lang/String;)Ljava/lang/StringBuilder;
    //   1646: pop
    //   1647: aload_3
    //   1648: invokevirtual toString : ()Ljava/lang/String;
    //   1651: putstatic com/laiqian/pos/hardware/RootUrlParameter.cle : Ljava/lang/String;
    //   1654: new java/lang/StringBuilder
    //   1657: dup
    //   1658: invokespecial <init> : ()V
    //   1661: astore_3
    //   1662: aload_3
    //   1663: getstatic com/laiqian/pos/hardware/RootUrlParameter.cld : Ljava/lang/String;
    //   1666: invokevirtual append : (Ljava/lang/String;)Ljava/lang/StringBuilder;
    //   1669: pop
    //   1670: aload_3
    //   1671: ldc_w '/version/info-more'
    //   1674: invokevirtual append : (Ljava/lang/String;)Ljava/lang/StringBuilder;
    //   1677: pop
    //   1678: aload_3
    //   1679: invokevirtual toString : ()Ljava/lang/String;
    //   1682: putstatic com/laiqian/pos/hardware/RootUrlParameter.clf : Ljava/lang/String;
    //   1685: new java/lang/StringBuilder
    //   1688: dup
    //   1689: invokespecial <init> : ()V
    //   1692: astore_3
    //   1693: aload_3
    //   1694: getstatic com/laiqian/pos/hardware/RootUrlParameter.cld : Ljava/lang/String;
    //   1697: invokevirtual append : (Ljava/lang/String;)Ljava/lang/StringBuilder;
    //   1700: pop
    //   1701: aload_3
    //   1702: ldc_w '/version/reply-more'
    //   1705: invokevirtual append : (Ljava/lang/String;)Ljava/lang/StringBuilder;
    //   1708: pop
    //   1709: aload_3
    //   1710: invokevirtual toString : ()Ljava/lang/String;
    //   1713: putstatic com/laiqian/pos/hardware/RootUrlParameter.clg : Ljava/lang/String;
    //   1716: new java/lang/StringBuilder
    //   1719: dup
    //   1720: invokespecial <init> : ()V
    //   1723: astore_3
    //   1724: aload_3
    //   1725: getstatic com/laiqian/pos/hardware/RootUrlParameter.cld : Ljava/lang/String;
    //   1728: invokevirtual append : (Ljava/lang/String;)Ljava/lang/StringBuilder;
    //   1731: pop
    //   1732: aload_3
    //   1733: ldc_w '/version/comment'
    //   1736: invokevirtual append : (Ljava/lang/String;)Ljava/lang/StringBuilder;
    //   1739: pop
    //   1740: aload_3
    //   1741: invokevirtual toString : ()Ljava/lang/String;
    //   1744: putstatic com/laiqian/pos/hardware/RootUrlParameter.clh : Ljava/lang/String;
    //   1747: new java/lang/StringBuilder
    //   1750: dup
    //   1751: invokespecial <init> : ()V
    //   1754: astore_3
    //   1755: aload_3
    //   1756: getstatic com/laiqian/pos/hardware/RootUrlParameter.cld : Ljava/lang/String;
    //   1759: invokevirtual append : (Ljava/lang/String;)Ljava/lang/StringBuilder;
    //   1762: pop
    //   1763: aload_3
    //   1764: ldc_w '/version/reply'
    //   1767: invokevirtual append : (Ljava/lang/String;)Ljava/lang/StringBuilder;
    //   1770: pop
    //   1771: aload_3
    //   1772: invokevirtual toString : ()Ljava/lang/String;
    //   1775: putstatic com/laiqian/pos/hardware/RootUrlParameter.cli : Ljava/lang/String;
    //   1778: new java/lang/StringBuilder
    //   1781: dup
    //   1782: invokespecial <init> : ()V
    //   1785: astore_3
    //   1786: aload_3
    //   1787: getstatic com/laiqian/pos/hardware/RootUrlParameter.cld : Ljava/lang/String;
    //   1790: invokevirtual append : (Ljava/lang/String;)Ljava/lang/StringBuilder;
    //   1793: pop
    //   1794: aload_3
    //   1795: ldc_w '/version/comment-info'
    //   1798: invokevirtual append : (Ljava/lang/String;)Ljava/lang/StringBuilder;
    //   1801: pop
    //   1802: aload_3
    //   1803: invokevirtual toString : ()Ljava/lang/String;
    //   1806: putstatic com/laiqian/pos/hardware/RootUrlParameter.clj : Ljava/lang/String;
    //   1809: new java/lang/StringBuilder
    //   1812: dup
    //   1813: invokespecial <init> : ()V
    //   1816: astore_3
    //   1817: aload_3
    //   1818: getstatic com/laiqian/pos/hardware/RootUrlParameter.ckC : Ljava/lang/String;
    //   1821: invokevirtual append : (Ljava/lang/String;)Ljava/lang/StringBuilder;
    //   1824: pop
    //   1825: aload_3
    //   1826: ldc_w 'datacheck/file'
    //   1829: invokevirtual append : (Ljava/lang/String;)Ljava/lang/StringBuilder;
    //   1832: pop
    //   1833: aload_3
    //   1834: invokevirtual toString : ()Ljava/lang/String;
    //   1837: putstatic com/laiqian/pos/hardware/RootUrlParameter.ckH : Ljava/lang/String;
    //   1840: getstatic com/laiqian/pos/hardware/RootUrlParameter.ckK : I
    //   1843: istore_1
    //   1844: iconst_3
    //   1845: istore_0
    //   1846: iload_1
    //   1847: iconst_2
    //   1848: if_icmpne -> 1854
    //   1851: goto -> 1861
    //   1854: getstatic com/laiqian/pos/hardware/RootUrlParameter.ckK : I
    //   1857: istore_1
    //   1858: goto -> 1851
    //   1861: ldc_w 'http://developer.waimai.meituan.com'
    //   1864: putstatic com/laiqian/pos/hardware/RootUrlParameter.cln : Ljava/lang/String;
    //   1867: new java/lang/StringBuilder
    //   1870: dup
    //   1871: invokespecial <init> : ()V
    //   1874: astore_3
    //   1875: aload_3
    //   1876: getstatic com/laiqian/pos/hardware/RootUrlParameter.ckW : Ljava/lang/String;
    //   1879: invokevirtual append : (Ljava/lang/String;)Ljava/lang/StringBuilder;
    //   1882: pop
    //   1883: aload_3
    //   1884: ldc_w 'shop/koubei?id=%1$s&table_no=%2$s'
    //   1887: invokevirtual append : (Ljava/lang/String;)Ljava/lang/StringBuilder;
    //   1890: pop
    //   1891: aload_3
    //   1892: invokevirtual toString : ()Ljava/lang/String;
    //   1895: putstatic com/laiqian/pos/hardware/RootUrlParameter.clo : Ljava/lang/String;
    //   1898: new java/lang/StringBuilder
    //   1901: dup
    //   1902: invokespecial <init> : ()V
    //   1905: astore_3
    //   1906: aload_3
    //   1907: getstatic com/laiqian/pos/hardware/RootUrlParameter.ckW : Ljava/lang/String;
    //   1910: invokevirtual append : (Ljava/lang/String;)Ljava/lang/StringBuilder;
    //   1913: pop
    //   1914: aload_3
    //   1915: ldc_w 'shop/koubei?id=%1$s&type=scanorder&table_no=%2$s'
    //   1918: invokevirtual append : (Ljava/lang/String;)Ljava/lang/StringBuilder;
    //   1921: pop
    //   1922: aload_3
    //   1923: invokevirtual toString : ()Ljava/lang/String;
    //   1926: putstatic com/laiqian/pos/hardware/RootUrlParameter.clp : Ljava/lang/String;
    //   1929: new java/lang/StringBuilder
    //   1932: dup
    //   1933: invokespecial <init> : ()V
    //   1936: astore_3
    //   1937: aload_3
    //   1938: getstatic com/laiqian/pos/hardware/RootUrlParameter.ckW : Ljava/lang/String;
    //   1941: invokevirtual append : (Ljava/lang/String;)Ljava/lang/StringBuilder;
    //   1944: pop
    //   1945: aload_3
    //   1946: ldc_w 'shop/koubei?id=%1$s&type=scanorder&table_no=%2$s&ui_style=%3$s'
    //   1949: invokevirtual append : (Ljava/lang/String;)Ljava/lang/StringBuilder;
    //   1952: pop
    //   1953: aload_3
    //   1954: invokevirtual toString : ()Ljava/lang/String;
    //   1957: putstatic com/laiqian/pos/hardware/RootUrlParameter.clq : Ljava/lang/String;
    //   1960: new java/lang/StringBuilder
    //   1963: dup
    //   1964: invokespecial <init> : ()V
    //   1967: astore_3
    //   1968: aload_3
    //   1969: getstatic com/laiqian/pos/hardware/RootUrlParameter.ckV : Ljava/lang/String;
    //   1972: invokevirtual append : (Ljava/lang/String;)Ljava/lang/StringBuilder;
    //   1975: pop
    //   1976: aload_3
    //   1977: ldc_w 'order/'
    //   1980: invokevirtual append : (Ljava/lang/String;)Ljava/lang/StringBuilder;
    //   1983: pop
    //   1984: aload_3
    //   1985: invokevirtual toString : ()Ljava/lang/String;
    //   1988: putstatic com/laiqian/pos/hardware/RootUrlParameter.clr : Ljava/lang/String;
    //   1991: new java/lang/StringBuilder
    //   1994: dup
    //   1995: invokespecial <init> : ()V
    //   1998: astore_3
    //   1999: aload_3
    //   2000: getstatic com/laiqian/pos/hardware/RootUrlParameter.ckN : Ljava/lang/String;
    //   2003: invokevirtual append : (Ljava/lang/String;)Ljava/lang/StringBuilder;
    //   2006: pop
    //   2007: aload_3
    //   2008: ldc_w '/mail/index'
    //   2011: invokevirtual append : (Ljava/lang/String;)Ljava/lang/StringBuilder;
    //   2014: pop
    //   2015: aload_3
    //   2016: invokevirtual toString : ()Ljava/lang/String;
    //   2019: putstatic com/laiqian/pos/hardware/RootUrlParameter.cls : Ljava/lang/String;
    //   2022: getstatic com/laiqian/pos/hardware/RootUrlParameter.ckK : I
    //   2025: istore_2
    //   2026: iconst_5
    //   2027: istore_1
    //   2028: iload_2
    //   2029: iconst_4
    //   2030: if_icmpeq -> 2047
    //   2033: getstatic com/laiqian/pos/hardware/RootUrlParameter.ckK : I
    //   2036: iconst_5
    //   2037: if_icmpeq -> 2047
    //   2040: ldc_w 'http://91laiqian.oss-cn-qingdao.aliyuncs.com'
    //   2043: astore_3
    //   2044: goto -> 2051
    //   2047: ldc_w 'http://91laiqian-singapore.oss-ap-southeast-1.aliyuncs.com'
    //   2050: astore_3
    //   2051: aload_3
    //   2052: putstatic com/laiqian/pos/hardware/RootUrlParameter.agL : Ljava/lang/String;
    //   2055: getstatic com/laiqian/pos/hardware/RootUrlParameter.ckK : I
    //   2058: iconst_4
    //   2059: if_icmpeq -> 2076
    //   2062: getstatic com/laiqian/pos/hardware/RootUrlParameter.ckK : I
    //   2065: iconst_5
    //   2066: if_icmpeq -> 2076
    //   2069: ldc_w 'oss-cn-qingdao.aliyuncs.com'
    //   2072: astore_3
    //   2073: goto -> 2080
    //   2076: ldc_w 'oss-ap-southeast-1.aliyuncs.com'
    //   2079: astore_3
    //   2080: aload_3
    //   2081: putstatic com/laiqian/pos/hardware/RootUrlParameter.agM : Ljava/lang/String;
    //   2084: getstatic com/laiqian/pos/hardware/RootUrlParameter.ckK : I
    //   2087: iconst_4
    //   2088: if_icmpeq -> 2105
    //   2091: getstatic com/laiqian/pos/hardware/RootUrlParameter.ckK : I
    //   2094: iconst_5
    //   2095: if_icmpeq -> 2105
    //   2098: ldc_w '91laiqian-apk'
    //   2101: astore_3
    //   2102: goto -> 2109
    //   2105: ldc_w '91laiqian-singapore-cdn-image'
    //   2108: astore_3
    //   2109: aload_3
    //   2110: putstatic com/laiqian/pos/hardware/RootUrlParameter.clt : Ljava/lang/String;
    //   2113: getstatic com/laiqian/pos/hardware/RootUrlParameter.ckK : I
    //   2116: istore_2
    //   2117: iload_2
    //   2118: bipush #9
    //   2120: if_icmpeq -> 2169
    //   2123: iload_2
    //   2124: tableswitch default -> 2148, 4 -> 2169, 5 -> 2169
    //   2148: ldc_w 'http://91laiqian.oss-cn-qingdao.aliyuncs.com'
    //   2151: putstatic com/laiqian/pos/hardware/RootUrlParameter.agL : Ljava/lang/String;
    //   2154: ldc_w 'oss-cn-qingdao.aliyuncs.com'
    //   2157: putstatic com/laiqian/pos/hardware/RootUrlParameter.agM : Ljava/lang/String;
    //   2160: ldc_w '91laiqian-apk'
    //   2163: putstatic com/laiqian/pos/hardware/RootUrlParameter.clt : Ljava/lang/String;
    //   2166: goto -> 2187
    //   2169: ldc_w 'http://91laiqian-singapore.oss-ap-southeast-1.aliyuncs.com'
    //   2172: putstatic com/laiqian/pos/hardware/RootUrlParameter.agL : Ljava/lang/String;
    //   2175: ldc_w 'oss-ap-southeast-1.aliyuncs.com'
    //   2178: putstatic com/laiqian/pos/hardware/RootUrlParameter.agM : Ljava/lang/String;
    //   2181: ldc_w '91laiqian-singapore-cdn-image'
    //   2184: putstatic com/laiqian/pos/hardware/RootUrlParameter.clt : Ljava/lang/String;
    //   2187: new java/lang/StringBuilder
    //   2190: dup
    //   2191: invokespecial <init> : ()V
    //   2194: astore_3
    //   2195: aload_3
    //   2196: getstatic com/laiqian/pos/hardware/RootUrlParameter.ckN : Ljava/lang/String;
    //   2199: invokevirtual append : (Ljava/lang/String;)Ljava/lang/StringBuilder;
    //   2202: pop
    //   2203: aload_3
    //   2204: ldc_w '/mall/index'
    //   2207: invokevirtual append : (Ljava/lang/String;)Ljava/lang/StringBuilder;
    //   2210: pop
    //   2211: aload_3
    //   2212: invokevirtual toString : ()Ljava/lang/String;
    //   2215: putstatic com/laiqian/pos/hardware/RootUrlParameter.clu : Ljava/lang/String;
    //   2218: new java/lang/StringBuilder
    //   2221: dup
    //   2222: invokespecial <init> : ()V
    //   2225: astore_3
    //   2226: aload_3
    //   2227: getstatic com/laiqian/pos/hardware/RootUrlParameter.ckN : Ljava/lang/String;
    //   2230: invokevirtual append : (Ljava/lang/String;)Ljava/lang/StringBuilder;
    //   2233: pop
    //   2234: aload_3
    //   2235: ldc_w '/message/introduction?id='
    //   2238: invokevirtual append : (Ljava/lang/String;)Ljava/lang/StringBuilder;
    //   2241: pop
    //   2242: aload_3
    //   2243: invokevirtual toString : ()Ljava/lang/String;
    //   2246: putstatic com/laiqian/pos/hardware/RootUrlParameter.clv : Ljava/lang/String;
    //   2249: new java/lang/StringBuilder
    //   2252: dup
    //   2253: invokespecial <init> : ()V
    //   2256: astore_3
    //   2257: aload_3
    //   2258: getstatic com/laiqian/pos/hardware/RootUrlParameter.ckN : Ljava/lang/String;
    //   2261: invokevirtual append : (Ljava/lang/String;)Ljava/lang/StringBuilder;
    //   2264: pop
    //   2265: aload_3
    //   2266: ldc_w '/data/delete'
    //   2269: invokevirtual append : (Ljava/lang/String;)Ljava/lang/StringBuilder;
    //   2272: pop
    //   2273: aload_3
    //   2274: invokevirtual toString : ()Ljava/lang/String;
    //   2277: putstatic com/laiqian/pos/hardware/RootUrlParameter.clw : Ljava/lang/String;
    //   2280: new java/lang/StringBuilder
    //   2283: dup
    //   2284: invokespecial <init> : ()V
    //   2287: astore_3
    //   2288: aload_3
    //   2289: getstatic com/laiqian/pos/hardware/RootUrlParameter.ckN : Ljava/lang/String;
    //   2292: invokevirtual append : (Ljava/lang/String;)Ljava/lang/StringBuilder;
    //   2295: pop
    //   2296: aload_3
    //   2297: ldc_w '/vip/updatesettings'
    //   2300: invokevirtual append : (Ljava/lang/String;)Ljava/lang/StringBuilder;
    //   2303: pop
    //   2304: aload_3
    //   2305: invokevirtual toString : ()Ljava/lang/String;
    //   2308: putstatic com/laiqian/pos/hardware/RootUrlParameter.clx : Ljava/lang/String;
    //   2311: new java/lang/StringBuilder
    //   2314: dup
    //   2315: invokespecial <init> : ()V
    //   2318: astore_3
    //   2319: aload_3
    //   2320: getstatic com/laiqian/pos/hardware/RootUrlParameter.ckN : Ljava/lang/String;
    //   2323: invokevirtual append : (Ljava/lang/String;)Ljava/lang/StringBuilder;
    //   2326: pop
    //   2327: aload_3
    //   2328: ldc_w '/vip/getsettings'
    //   2331: invokevirtual append : (Ljava/lang/String;)Ljava/lang/StringBuilder;
    //   2334: pop
    //   2335: aload_3
    //   2336: invokevirtual toString : ()Ljava/lang/String;
    //   2339: putstatic com/laiqian/pos/hardware/RootUrlParameter.cly : Ljava/lang/String;
    //   2342: new java/lang/StringBuilder
    //   2345: dup
    //   2346: invokespecial <init> : ()V
    //   2349: astore_3
    //   2350: aload_3
    //   2351: getstatic com/laiqian/pos/hardware/RootUrlParameter.ckN : Ljava/lang/String;
    //   2354: invokevirtual append : (Ljava/lang/String;)Ljava/lang/StringBuilder;
    //   2357: pop
    //   2358: aload_3
    //   2359: ldc_w '/points/updatesettings'
    //   2362: invokevirtual append : (Ljava/lang/String;)Ljava/lang/StringBuilder;
    //   2365: pop
    //   2366: aload_3
    //   2367: invokevirtual toString : ()Ljava/lang/String;
    //   2370: putstatic com/laiqian/pos/hardware/RootUrlParameter.clz : Ljava/lang/String;
    //   2373: new java/lang/StringBuilder
    //   2376: dup
    //   2377: invokespecial <init> : ()V
    //   2380: astore_3
    //   2381: aload_3
    //   2382: getstatic com/laiqian/pos/hardware/RootUrlParameter.ckN : Ljava/lang/String;
    //   2385: invokevirtual append : (Ljava/lang/String;)Ljava/lang/StringBuilder;
    //   2388: pop
    //   2389: aload_3
    //   2390: ldc_w '/points/getsettings'
    //   2393: invokevirtual append : (Ljava/lang/String;)Ljava/lang/StringBuilder;
    //   2396: pop
    //   2397: aload_3
    //   2398: invokevirtual toString : ()Ljava/lang/String;
    //   2401: putstatic com/laiqian/pos/hardware/RootUrlParameter.clA : Ljava/lang/String;
    //   2404: new java/lang/StringBuilder
    //   2407: dup
    //   2408: invokespecial <init> : ()V
    //   2411: astore_3
    //   2412: aload_3
    //   2413: getstatic com/laiqian/pos/hardware/RootUrlParameter.ckN : Ljava/lang/String;
    //   2416: invokevirtual append : (Ljava/lang/String;)Ljava/lang/StringBuilder;
    //   2419: pop
    //   2420: aload_3
    //   2421: ldc_w '/message/detail?id=1&type=system_update'
    //   2424: invokevirtual append : (Ljava/lang/String;)Ljava/lang/StringBuilder;
    //   2427: pop
    //   2428: aload_3
    //   2429: invokevirtual toString : ()Ljava/lang/String;
    //   2432: putstatic com/laiqian/pos/hardware/RootUrlParameter.clB : Ljava/lang/String;
    //   2435: new java/lang/StringBuilder
    //   2438: dup
    //   2439: invokespecial <init> : ()V
    //   2442: astore_3
    //   2443: aload_3
    //   2444: getstatic com/laiqian/pos/hardware/RootUrlParameter.ckN : Ljava/lang/String;
    //   2447: invokevirtual append : (Ljava/lang/String;)Ljava/lang/StringBuilder;
    //   2450: pop
    //   2451: aload_3
    //   2452: ldc_w '/vip/get-upgrade'
    //   2455: invokevirtual append : (Ljava/lang/String;)Ljava/lang/StringBuilder;
    //   2458: pop
    //   2459: aload_3
    //   2460: invokevirtual toString : ()Ljava/lang/String;
    //   2463: putstatic com/laiqian/pos/hardware/RootUrlParameter.clC : Ljava/lang/String;
    //   2466: new java/lang/StringBuilder
    //   2469: dup
    //   2470: invokespecial <init> : ()V
    //   2473: astore_3
    //   2474: aload_3
    //   2475: getstatic com/laiqian/pos/hardware/RootUrlParameter.ckC : Ljava/lang/String;
    //   2478: invokevirtual append : (Ljava/lang/String;)Ljava/lang/StringBuilder;
    //   2481: pop
    //   2482: aload_3
    //   2483: ldc_w '/bpartner/all-member'
    //   2486: invokevirtual append : (Ljava/lang/String;)Ljava/lang/StringBuilder;
    //   2489: pop
    //   2490: aload_3
    //   2491: invokevirtual toString : ()Ljava/lang/String;
    //   2494: putstatic com/laiqian/pos/hardware/RootUrlParameter.clD : Ljava/lang/String;
    //   2497: new java/lang/StringBuilder
    //   2500: dup
    //   2501: invokespecial <init> : ()V
    //   2504: astore_3
    //   2505: aload_3
    //   2506: getstatic com/laiqian/pos/hardware/RootUrlParameter.ckN : Ljava/lang/String;
    //   2509: invokevirtual append : (Ljava/lang/String;)Ljava/lang/StringBuilder;
    //   2512: pop
    //   2513: aload_3
    //   2514: ldc_w '/vip/get-sms-setting'
    //   2517: invokevirtual append : (Ljava/lang/String;)Ljava/lang/StringBuilder;
    //   2520: pop
    //   2521: aload_3
    //   2522: invokevirtual toString : ()Ljava/lang/String;
    //   2525: putstatic com/laiqian/pos/hardware/RootUrlParameter.clE : Ljava/lang/String;
    //   2528: new java/lang/StringBuilder
    //   2531: dup
    //   2532: invokespecial <init> : ()V
    //   2535: astore_3
    //   2536: aload_3
    //   2537: getstatic com/laiqian/pos/hardware/RootUrlParameter.ckN : Ljava/lang/String;
    //   2540: invokevirtual append : (Ljava/lang/String;)Ljava/lang/StringBuilder;
    //   2543: pop
    //   2544: aload_3
    //   2545: ldc_w '/vip/get-sms-quantity-left'
    //   2548: invokevirtual append : (Ljava/lang/String;)Ljava/lang/StringBuilder;
    //   2551: pop
    //   2552: aload_3
    //   2553: invokevirtual toString : ()Ljava/lang/String;
    //   2556: putstatic com/laiqian/pos/hardware/RootUrlParameter.clF : Ljava/lang/String;
    //   2559: new java/lang/StringBuilder
    //   2562: dup
    //   2563: invokespecial <init> : ()V
    //   2566: astore_3
    //   2567: aload_3
    //   2568: getstatic com/laiqian/pos/hardware/RootUrlParameter.ckN : Ljava/lang/String;
    //   2571: invokevirtual append : (Ljava/lang/String;)Ljava/lang/StringBuilder;
    //   2574: pop
    //   2575: aload_3
    //   2576: ldc_w '/vip/send-message-by-sms'
    //   2579: invokevirtual append : (Ljava/lang/String;)Ljava/lang/StringBuilder;
    //   2582: pop
    //   2583: aload_3
    //   2584: invokevirtual toString : ()Ljava/lang/String;
    //   2587: putstatic com/laiqian/pos/hardware/RootUrlParameter.clG : Ljava/lang/String;
    //   2590: new java/lang/StringBuilder
    //   2593: dup
    //   2594: invokespecial <init> : ()V
    //   2597: astore_3
    //   2598: aload_3
    //   2599: getstatic com/laiqian/pos/hardware/RootUrlParameter.ckN : Ljava/lang/String;
    //   2602: invokevirtual append : (Ljava/lang/String;)Ljava/lang/StringBuilder;
    //   2605: pop
    //   2606: aload_3
    //   2607: ldc_w '/vip/send-mass-discount-messages'
    //   2610: invokevirtual append : (Ljava/lang/String;)Ljava/lang/StringBuilder;
    //   2613: pop
    //   2614: aload_3
    //   2615: invokevirtual toString : ()Ljava/lang/String;
    //   2618: putstatic com/laiqian/pos/hardware/RootUrlParameter.clH : Ljava/lang/String;
    //   2621: new java/lang/StringBuilder
    //   2624: dup
    //   2625: invokespecial <init> : ()V
    //   2628: astore_3
    //   2629: aload_3
    //   2630: getstatic com/laiqian/pos/hardware/RootUrlParameter.ckN : Ljava/lang/String;
    //   2633: invokevirtual append : (Ljava/lang/String;)Ljava/lang/StringBuilder;
    //   2636: pop
    //   2637: aload_3
    //   2638: ldc_w '/vip/show-send-list'
    //   2641: invokevirtual append : (Ljava/lang/String;)Ljava/lang/StringBuilder;
    //   2644: pop
    //   2645: aload_3
    //   2646: invokevirtual toString : ()Ljava/lang/String;
    //   2649: putstatic com/laiqian/pos/hardware/RootUrlParameter.clI : Ljava/lang/String;
    //   2652: new java/lang/StringBuilder
    //   2655: dup
    //   2656: invokespecial <init> : ()V
    //   2659: astore_3
    //   2660: aload_3
    //   2661: getstatic com/laiqian/pos/hardware/RootUrlParameter.ckN : Ljava/lang/String;
    //   2664: invokevirtual append : (Ljava/lang/String;)Ljava/lang/StringBuilder;
    //   2667: pop
    //   2668: aload_3
    //   2669: ldc_w '/vip/update-sms-setting'
    //   2672: invokevirtual append : (Ljava/lang/String;)Ljava/lang/StringBuilder;
    //   2675: pop
    //   2676: aload_3
    //   2677: invokevirtual toString : ()Ljava/lang/String;
    //   2680: putstatic com/laiqian/pos/hardware/RootUrlParameter.clJ : Ljava/lang/String;
    //   2683: new java/lang/StringBuilder
    //   2686: dup
    //   2687: invokespecial <init> : ()V
    //   2690: astore_3
    //   2691: aload_3
    //   2692: getstatic com/laiqian/pos/hardware/RootUrlParameter.ckN : Ljava/lang/String;
    //   2695: invokevirtual append : (Ljava/lang/String;)Ljava/lang/StringBuilder;
    //   2698: pop
    //   2699: aload_3
    //   2700: ldc_w '/vip/update-sms-quantity-left'
    //   2703: invokevirtual append : (Ljava/lang/String;)Ljava/lang/StringBuilder;
    //   2706: pop
    //   2707: aload_3
    //   2708: invokevirtual toString : ()Ljava/lang/String;
    //   2711: putstatic com/laiqian/pos/hardware/RootUrlParameter.clK : Ljava/lang/String;
    //   2714: new java/lang/StringBuilder
    //   2717: dup
    //   2718: invokespecial <init> : ()V
    //   2721: astore_3
    //   2722: aload_3
    //   2723: getstatic com/laiqian/pos/hardware/RootUrlParameter.ckN : Ljava/lang/String;
    //   2726: invokevirtual append : (Ljava/lang/String;)Ljava/lang/StringBuilder;
    //   2729: pop
    //   2730: aload_3
    //   2731: ldc_w '/vip/update-upgrade'
    //   2734: invokevirtual append : (Ljava/lang/String;)Ljava/lang/StringBuilder;
    //   2737: pop
    //   2738: aload_3
    //   2739: invokevirtual toString : ()Ljava/lang/String;
    //   2742: putstatic com/laiqian/pos/hardware/RootUrlParameter.clL : Ljava/lang/String;
    //   2745: new java/lang/StringBuilder
    //   2748: dup
    //   2749: invokespecial <init> : ()V
    //   2752: astore_3
    //   2753: aload_3
    //   2754: getstatic com/laiqian/pos/hardware/RootUrlParameter.ckC : Ljava/lang/String;
    //   2757: invokevirtual append : (Ljava/lang/String;)Ljava/lang/StringBuilder;
    //   2760: pop
    //   2761: aload_3
    //   2762: ldc_w '/bpartner/get-level'
    //   2765: invokevirtual append : (Ljava/lang/String;)Ljava/lang/StringBuilder;
    //   2768: pop
    //   2769: aload_3
    //   2770: invokevirtual toString : ()Ljava/lang/String;
    //   2773: putstatic com/laiqian/pos/hardware/RootUrlParameter.clM : Ljava/lang/String;
    //   2776: new java/lang/StringBuilder
    //   2779: dup
    //   2780: invokespecial <init> : ()V
    //   2783: astore_3
    //   2784: aload_3
    //   2785: getstatic com/laiqian/pos/hardware/RootUrlParameter.ckC : Ljava/lang/String;
    //   2788: invokevirtual append : (Ljava/lang/String;)Ljava/lang/StringBuilder;
    //   2791: pop
    //   2792: aload_3
    //   2793: ldc_w '/bpartner/update-level'
    //   2796: invokevirtual append : (Ljava/lang/String;)Ljava/lang/StringBuilder;
    //   2799: pop
    //   2800: aload_3
    //   2801: invokevirtual toString : ()Ljava/lang/String;
    //   2804: putstatic com/laiqian/pos/hardware/RootUrlParameter.clN : Ljava/lang/String;
    //   2807: new java/lang/StringBuilder
    //   2810: dup
    //   2811: invokespecial <init> : ()V
    //   2814: astore_3
    //   2815: aload_3
    //   2816: getstatic com/laiqian/pos/hardware/RootUrlParameter.ckN : Ljava/lang/String;
    //   2819: invokevirtual append : (Ljava/lang/String;)Ljava/lang/StringBuilder;
    //   2822: pop
    //   2823: aload_3
    //   2824: ldc_w '/vip/update-lqk-config'
    //   2827: invokevirtual append : (Ljava/lang/String;)Ljava/lang/StringBuilder;
    //   2830: pop
    //   2831: aload_3
    //   2832: invokevirtual toString : ()Ljava/lang/String;
    //   2835: putstatic com/laiqian/pos/hardware/RootUrlParameter.clO : Ljava/lang/String;
    //   2838: new java/lang/StringBuilder
    //   2841: dup
    //   2842: invokespecial <init> : ()V
    //   2845: astore_3
    //   2846: aload_3
    //   2847: getstatic com/laiqian/pos/hardware/RootUrlParameter.ckN : Ljava/lang/String;
    //   2850: invokevirtual append : (Ljava/lang/String;)Ljava/lang/StringBuilder;
    //   2853: pop
    //   2854: aload_3
    //   2855: ldc_w '/vip/validate'
    //   2858: invokevirtual append : (Ljava/lang/String;)Ljava/lang/StringBuilder;
    //   2861: pop
    //   2862: aload_3
    //   2863: invokevirtual toString : ()Ljava/lang/String;
    //   2866: putstatic com/laiqian/pos/hardware/RootUrlParameter.clP : Ljava/lang/String;
    //   2869: new java/lang/StringBuilder
    //   2872: dup
    //   2873: invokespecial <init> : ()V
    //   2876: astore_3
    //   2877: aload_3
    //   2878: getstatic com/laiqian/pos/hardware/RootUrlParameter.ckN : Ljava/lang/String;
    //   2881: invokevirtual append : (Ljava/lang/String;)Ljava/lang/StringBuilder;
    //   2884: pop
    //   2885: aload_3
    //   2886: ldc_w '/search/index'
    //   2889: invokevirtual append : (Ljava/lang/String;)Ljava/lang/StringBuilder;
    //   2892: pop
    //   2893: aload_3
    //   2894: invokevirtual toString : ()Ljava/lang/String;
    //   2897: putstatic com/laiqian/pos/hardware/RootUrlParameter.clQ : Ljava/lang/String;
    //   2900: new java/lang/StringBuilder
    //   2903: dup
    //   2904: invokespecial <init> : ()V
    //   2907: astore_3
    //   2908: aload_3
    //   2909: getstatic com/laiqian/pos/hardware/RootUrlParameter.ckN : Ljava/lang/String;
    //   2912: invokevirtual append : (Ljava/lang/String;)Ljava/lang/StringBuilder;
    //   2915: pop
    //   2916: aload_3
    //   2917: ldc_w '/mall/detail?ID=8'
    //   2920: invokevirtual append : (Ljava/lang/String;)Ljava/lang/StringBuilder;
    //   2923: pop
    //   2924: aload_3
    //   2925: invokevirtual toString : ()Ljava/lang/String;
    //   2928: putstatic com/laiqian/pos/hardware/RootUrlParameter.clR : Ljava/lang/String;
    //   2931: new java/lang/StringBuilder
    //   2934: dup
    //   2935: invokespecial <init> : ()V
    //   2938: astore_3
    //   2939: aload_3
    //   2940: getstatic com/laiqian/pos/hardware/RootUrlParameter.ckN : Ljava/lang/String;
    //   2943: invokevirtual append : (Ljava/lang/String;)Ljava/lang/StringBuilder;
    //   2946: pop
    //   2947: aload_3
    //   2948: ldc_w '/message/detail?id=8&type=CanYin'
    //   2951: invokevirtual append : (Ljava/lang/String;)Ljava/lang/StringBuilder;
    //   2954: pop
    //   2955: aload_3
    //   2956: invokevirtual toString : ()Ljava/lang/String;
    //   2959: putstatic com/laiqian/pos/hardware/RootUrlParameter.clS : Ljava/lang/String;
    //   2962: new java/lang/StringBuilder
    //   2965: dup
    //   2966: invokespecial <init> : ()V
    //   2969: astore_3
    //   2970: aload_3
    //   2971: getstatic com/laiqian/pos/hardware/RootUrlParameter.ckN : Ljava/lang/String;
    //   2974: invokevirtual append : (Ljava/lang/String;)Ljava/lang/StringBuilder;
    //   2977: pop
    //   2978: aload_3
    //   2979: ldc_w '/update/index'
    //   2982: invokevirtual append : (Ljava/lang/String;)Ljava/lang/StringBuilder;
    //   2985: pop
    //   2986: aload_3
    //   2987: invokevirtual toString : ()Ljava/lang/String;
    //   2990: putstatic com/laiqian/pos/hardware/RootUrlParameter.clT : Ljava/lang/String;
    //   2993: new java/lang/StringBuilder
    //   2996: dup
    //   2997: invokespecial <init> : ()V
    //   3000: astore_3
    //   3001: aload_3
    //   3002: getstatic com/laiqian/pos/hardware/RootUrlParameter.ckP : Ljava/lang/String;
    //   3005: invokevirtual append : (Ljava/lang/String;)Ljava/lang/StringBuilder;
    //   3008: pop
    //   3009: aload_3
    //   3010: ldc_w '/message/detail?id=18&type=order_introduction'
    //   3013: invokevirtual append : (Ljava/lang/String;)Ljava/lang/StringBuilder;
    //   3016: pop
    //   3017: aload_3
    //   3018: invokevirtual toString : ()Ljava/lang/String;
    //   3021: putstatic com/laiqian/pos/hardware/RootUrlParameter.clU : Ljava/lang/String;
    //   3024: new java/lang/StringBuilder
    //   3027: dup
    //   3028: invokespecial <init> : ()V
    //   3031: astore_3
    //   3032: aload_3
    //   3033: getstatic com/laiqian/pos/hardware/RootUrlParameter.ckD : Ljava/lang/String;
    //   3036: invokevirtual append : (Ljava/lang/String;)Ljava/lang/StringBuilder;
    //   3039: pop
    //   3040: aload_3
    //   3041: ldc_w 'order/tables'
    //   3044: invokevirtual append : (Ljava/lang/String;)Ljava/lang/StringBuilder;
    //   3047: pop
    //   3048: aload_3
    //   3049: invokevirtual toString : ()Ljava/lang/String;
    //   3052: putstatic com/laiqian/pos/hardware/RootUrlParameter.clV : Ljava/lang/String;
    //   3055: new java/lang/StringBuilder
    //   3058: dup
    //   3059: invokespecial <init> : ()V
    //   3062: astore_3
    //   3063: aload_3
    //   3064: getstatic com/laiqian/pos/hardware/RootUrlParameter.ckD : Ljava/lang/String;
    //   3067: invokevirtual append : (Ljava/lang/String;)Ljava/lang/StringBuilder;
    //   3070: pop
    //   3071: aload_3
    //   3072: ldc_w 'order/order'
    //   3075: invokevirtual append : (Ljava/lang/String;)Ljava/lang/StringBuilder;
    //   3078: pop
    //   3079: aload_3
    //   3080: invokevirtual toString : ()Ljava/lang/String;
    //   3083: putstatic com/laiqian/pos/hardware/RootUrlParameter.clW : Ljava/lang/String;
    //   3086: new java/lang/StringBuilder
    //   3089: dup
    //   3090: invokespecial <init> : ()V
    //   3093: astore_3
    //   3094: aload_3
    //   3095: getstatic com/laiqian/pos/hardware/RootUrlParameter.ckD : Ljava/lang/String;
    //   3098: invokevirtual append : (Ljava/lang/String;)Ljava/lang/StringBuilder;
    //   3101: pop
    //   3102: aload_3
    //   3103: ldc_w 'order/confirm'
    //   3106: invokevirtual append : (Ljava/lang/String;)Ljava/lang/StringBuilder;
    //   3109: pop
    //   3110: aload_3
    //   3111: invokevirtual toString : ()Ljava/lang/String;
    //   3114: putstatic com/laiqian/pos/hardware/RootUrlParameter.clX : Ljava/lang/String;
    //   3117: new java/lang/StringBuilder
    //   3120: dup
    //   3121: invokespecial <init> : ()V
    //   3124: astore_3
    //   3125: aload_3
    //   3126: getstatic com/laiqian/pos/hardware/RootUrlParameter.ckD : Ljava/lang/String;
    //   3129: invokevirtual append : (Ljava/lang/String;)Ljava/lang/StringBuilder;
    //   3132: pop
    //   3133: aload_3
    //   3134: ldc_w 'order/check-table'
    //   3137: invokevirtual append : (Ljava/lang/String;)Ljava/lang/StringBuilder;
    //   3140: pop
    //   3141: aload_3
    //   3142: invokevirtual toString : ()Ljava/lang/String;
    //   3145: putstatic com/laiqian/pos/hardware/RootUrlParameter.clY : Ljava/lang/String;
    //   3148: new java/lang/StringBuilder
    //   3151: dup
    //   3152: invokespecial <init> : ()V
    //   3155: astore_3
    //   3156: aload_3
    //   3157: getstatic com/laiqian/pos/hardware/RootUrlParameter.ckD : Ljava/lang/String;
    //   3160: invokevirtual append : (Ljava/lang/String;)Ljava/lang/StringBuilder;
    //   3163: pop
    //   3164: aload_3
    //   3165: ldc_w 'order/delete-order'
    //   3168: invokevirtual append : (Ljava/lang/String;)Ljava/lang/StringBuilder;
    //   3171: pop
    //   3172: aload_3
    //   3173: invokevirtual toString : ()Ljava/lang/String;
    //   3176: putstatic com/laiqian/pos/hardware/RootUrlParameter.clZ : Ljava/lang/String;
    //   3179: new java/lang/StringBuilder
    //   3182: dup
    //   3183: invokespecial <init> : ()V
    //   3186: astore_3
    //   3187: aload_3
    //   3188: getstatic com/laiqian/pos/hardware/RootUrlParameter.ckD : Ljava/lang/String;
    //   3191: invokevirtual append : (Ljava/lang/String;)Ljava/lang/StringBuilder;
    //   3194: pop
    //   3195: aload_3
    //   3196: ldc_w 'order/complete-order'
    //   3199: invokevirtual append : (Ljava/lang/String;)Ljava/lang/StringBuilder;
    //   3202: pop
    //   3203: aload_3
    //   3204: invokevirtual toString : ()Ljava/lang/String;
    //   3207: putstatic com/laiqian/pos/hardware/RootUrlParameter.cma : Ljava/lang/String;
    //   3210: new java/lang/StringBuilder
    //   3213: dup
    //   3214: invokespecial <init> : ()V
    //   3217: astore_3
    //   3218: aload_3
    //   3219: getstatic com/laiqian/pos/hardware/RootUrlParameter.ckD : Ljava/lang/String;
    //   3222: invokevirtual append : (Ljava/lang/String;)Ljava/lang/StringBuilder;
    //   3225: pop
    //   3226: aload_3
    //   3227: ldc_w 'order/change-table'
    //   3230: invokevirtual append : (Ljava/lang/String;)Ljava/lang/StringBuilder;
    //   3233: pop
    //   3234: aload_3
    //   3235: invokevirtual toString : ()Ljava/lang/String;
    //   3238: putstatic com/laiqian/pos/hardware/RootUrlParameter.cmb : Ljava/lang/String;
    //   3241: new java/lang/StringBuilder
    //   3244: dup
    //   3245: invokespecial <init> : ()V
    //   3248: astore_3
    //   3249: aload_3
    //   3250: getstatic com/laiqian/pos/hardware/RootUrlParameter.ckD : Ljava/lang/String;
    //   3253: invokevirtual append : (Ljava/lang/String;)Ljava/lang/StringBuilder;
    //   3256: pop
    //   3257: aload_3
    //   3258: ldc_w 'device/register'
    //   3261: invokevirtual append : (Ljava/lang/String;)Ljava/lang/StringBuilder;
    //   3264: pop
    //   3265: aload_3
    //   3266: invokevirtual toString : ()Ljava/lang/String;
    //   3269: putstatic com/laiqian/pos/hardware/RootUrlParameter.cmc : Ljava/lang/String;
    //   3272: new java/lang/StringBuilder
    //   3275: dup
    //   3276: invokespecial <init> : ()V
    //   3279: astore_3
    //   3280: aload_3
    //   3281: getstatic com/laiqian/pos/hardware/RootUrlParameter.ckD : Ljava/lang/String;
    //   3284: invokevirtual append : (Ljava/lang/String;)Ljava/lang/StringBuilder;
    //   3287: pop
    //   3288: aload_3
    //   3289: ldc_w 'order/unfinished-order'
    //   3292: invokevirtual append : (Ljava/lang/String;)Ljava/lang/StringBuilder;
    //   3295: pop
    //   3296: aload_3
    //   3297: invokevirtual toString : ()Ljava/lang/String;
    //   3300: putstatic com/laiqian/pos/hardware/RootUrlParameter.cme : Ljava/lang/String;
    //   3303: new java/lang/StringBuilder
    //   3306: dup
    //   3307: invokespecial <init> : ()V
    //   3310: astore_3
    //   3311: aload_3
    //   3312: getstatic com/laiqian/pos/hardware/RootUrlParameter.ckD : Ljava/lang/String;
    //   3315: invokevirtual append : (Ljava/lang/String;)Ljava/lang/StringBuilder;
    //   3318: pop
    //   3319: aload_3
    //   3320: ldc_w 'order/status-push'
    //   3323: invokevirtual append : (Ljava/lang/String;)Ljava/lang/StringBuilder;
    //   3326: pop
    //   3327: aload_3
    //   3328: invokevirtual toString : ()Ljava/lang/String;
    //   3331: putstatic com/laiqian/pos/hardware/RootUrlParameter.cmf : Ljava/lang/String;
    //   3334: new java/lang/StringBuilder
    //   3337: dup
    //   3338: invokespecial <init> : ()V
    //   3341: astore_3
    //   3342: aload_3
    //   3343: getstatic com/laiqian/pos/hardware/RootUrlParameter.ckD : Ljava/lang/String;
    //   3346: invokevirtual append : (Ljava/lang/String;)Ljava/lang/StringBuilder;
    //   3349: pop
    //   3350: aload_3
    //   3351: ldc_w 'order/all-order'
    //   3354: invokevirtual append : (Ljava/lang/String;)Ljava/lang/StringBuilder;
    //   3357: pop
    //   3358: aload_3
    //   3359: invokevirtual toString : ()Ljava/lang/String;
    //   3362: putstatic com/laiqian/pos/hardware/RootUrlParameter.cmg : Ljava/lang/String;
    //   3365: new java/lang/StringBuilder
    //   3368: dup
    //   3369: invokespecial <init> : ()V
    //   3372: astore_3
    //   3373: aload_3
    //   3374: getstatic com/laiqian/pos/hardware/RootUrlParameter.ckD : Ljava/lang/String;
    //   3377: invokevirtual append : (Ljava/lang/String;)Ljava/lang/StringBuilder;
    //   3380: pop
    //   3381: aload_3
    //   3382: ldc_w 'order/all-confirm'
    //   3385: invokevirtual append : (Ljava/lang/String;)Ljava/lang/StringBuilder;
    //   3388: pop
    //   3389: aload_3
    //   3390: invokevirtual toString : ()Ljava/lang/String;
    //   3393: putstatic com/laiqian/pos/hardware/RootUrlParameter.cmh : Ljava/lang/String;
    //   3396: new java/lang/StringBuilder
    //   3399: dup
    //   3400: invokespecial <init> : ()V
    //   3403: astore_3
    //   3404: aload_3
    //   3405: getstatic com/laiqian/pos/hardware/RootUrlParameter.ckD : Ljava/lang/String;
    //   3408: invokevirtual append : (Ljava/lang/String;)Ljava/lang/StringBuilder;
    //   3411: pop
    //   3412: aload_3
    //   3413: ldc_w 'order/delete-all-order'
    //   3416: invokevirtual append : (Ljava/lang/String;)Ljava/lang/StringBuilder;
    //   3419: pop
    //   3420: aload_3
    //   3421: invokevirtual toString : ()Ljava/lang/String;
    //   3424: putstatic com/laiqian/pos/hardware/RootUrlParameter.cmi : Ljava/lang/String;
    //   3427: new java/lang/StringBuilder
    //   3430: dup
    //   3431: invokespecial <init> : ()V
    //   3434: astore_3
    //   3435: aload_3
    //   3436: getstatic com/laiqian/pos/hardware/RootUrlParameter.ckD : Ljava/lang/String;
    //   3439: invokevirtual append : (Ljava/lang/String;)Ljava/lang/StringBuilder;
    //   3442: pop
    //   3443: aload_3
    //   3444: ldc_w 'scan-order/pending-order'
    //   3447: invokevirtual append : (Ljava/lang/String;)Ljava/lang/StringBuilder;
    //   3450: pop
    //   3451: aload_3
    //   3452: invokevirtual toString : ()Ljava/lang/String;
    //   3455: putstatic com/laiqian/pos/hardware/RootUrlParameter.cmj : Ljava/lang/String;
    //   3458: new java/lang/StringBuilder
    //   3461: dup
    //   3462: invokespecial <init> : ()V
    //   3465: astore_3
    //   3466: aload_3
    //   3467: getstatic com/laiqian/pos/hardware/RootUrlParameter.ckV : Ljava/lang/String;
    //   3470: invokevirtual append : (Ljava/lang/String;)Ljava/lang/StringBuilder;
    //   3473: pop
    //   3474: aload_3
    //   3475: ldc_w 'scanorder/client-all-orders'
    //   3478: invokevirtual append : (Ljava/lang/String;)Ljava/lang/StringBuilder;
    //   3481: pop
    //   3482: aload_3
    //   3483: invokevirtual toString : ()Ljava/lang/String;
    //   3486: putstatic com/laiqian/pos/hardware/RootUrlParameter.cmk : Ljava/lang/String;
    //   3489: new java/lang/StringBuilder
    //   3492: dup
    //   3493: invokespecial <init> : ()V
    //   3496: astore_3
    //   3497: aload_3
    //   3498: getstatic com/laiqian/pos/hardware/RootUrlParameter.ckV : Ljava/lang/String;
    //   3501: invokevirtual append : (Ljava/lang/String;)Ljava/lang/StringBuilder;
    //   3504: pop
    //   3505: aload_3
    //   3506: ldc_w 'scanorder/operate-pending-order'
    //   3509: invokevirtual append : (Ljava/lang/String;)Ljava/lang/StringBuilder;
    //   3512: pop
    //   3513: aload_3
    //   3514: invokevirtual toString : ()Ljava/lang/String;
    //   3517: putstatic com/laiqian/pos/hardware/RootUrlParameter.cml : Ljava/lang/String;
    //   3520: new java/lang/StringBuilder
    //   3523: dup
    //   3524: invokespecial <init> : ()V
    //   3527: astore_3
    //   3528: aload_3
    //   3529: getstatic com/laiqian/pos/hardware/RootUrlParameter.ckD : Ljava/lang/String;
    //   3532: invokevirtual append : (Ljava/lang/String;)Ljava/lang/StringBuilder;
    //   3535: pop
    //   3536: aload_3
    //   3537: ldc_w 'order/complete-order'
    //   3540: invokevirtual append : (Ljava/lang/String;)Ljava/lang/StringBuilder;
    //   3543: pop
    //   3544: aload_3
    //   3545: invokevirtual toString : ()Ljava/lang/String;
    //   3548: putstatic com/laiqian/pos/hardware/RootUrlParameter.cmm : Ljava/lang/String;
    //   3551: new java/lang/StringBuilder
    //   3554: dup
    //   3555: invokespecial <init> : ()V
    //   3558: astore_3
    //   3559: aload_3
    //   3560: getstatic com/laiqian/pos/hardware/RootUrlParameter.ckD : Ljava/lang/String;
    //   3563: invokevirtual append : (Ljava/lang/String;)Ljava/lang/StringBuilder;
    //   3566: pop
    //   3567: aload_3
    //   3568: ldc_w 'scan-order/edit-order'
    //   3571: invokevirtual append : (Ljava/lang/String;)Ljava/lang/StringBuilder;
    //   3574: pop
    //   3575: aload_3
    //   3576: invokevirtual toString : ()Ljava/lang/String;
    //   3579: putstatic com/laiqian/pos/hardware/RootUrlParameter.cmn : Ljava/lang/String;
    //   3582: new java/lang/StringBuilder
    //   3585: dup
    //   3586: invokespecial <init> : ()V
    //   3589: astore_3
    //   3590: aload_3
    //   3591: getstatic com/laiqian/pos/hardware/RootUrlParameter.ckX : Ljava/lang/String;
    //   3594: invokevirtual append : (Ljava/lang/String;)Ljava/lang/StringBuilder;
    //   3597: pop
    //   3598: aload_3
    //   3599: ldc_w 'news/scan-order-status'
    //   3602: invokevirtual append : (Ljava/lang/String;)Ljava/lang/StringBuilder;
    //   3605: pop
    //   3606: aload_3
    //   3607: invokevirtual toString : ()Ljava/lang/String;
    //   3610: putstatic com/laiqian/pos/hardware/RootUrlParameter.cmo : Ljava/lang/String;
    //   3613: new java/lang/StringBuilder
    //   3616: dup
    //   3617: invokespecial <init> : ()V
    //   3620: astore_3
    //   3621: aload_3
    //   3622: getstatic com/laiqian/pos/hardware/RootUrlParameter.ckS : Ljava/lang/String;
    //   3625: invokevirtual append : (Ljava/lang/String;)Ljava/lang/StringBuilder;
    //   3628: pop
    //   3629: aload_3
    //   3630: ldc_w 'onlinepaybind/qrcode'
    //   3633: invokevirtual append : (Ljava/lang/String;)Ljava/lang/StringBuilder;
    //   3636: pop
    //   3637: aload_3
    //   3638: invokevirtual toString : ()Ljava/lang/String;
    //   3641: putstatic com/laiqian/pos/hardware/RootUrlParameter.cmp : Ljava/lang/String;
    //   3644: new java/lang/StringBuilder
    //   3647: dup
    //   3648: invokespecial <init> : ()V
    //   3651: astore_3
    //   3652: aload_3
    //   3653: getstatic com/laiqian/pos/hardware/RootUrlParameter.ckS : Ljava/lang/String;
    //   3656: invokevirtual append : (Ljava/lang/String;)Ljava/lang/StringBuilder;
    //   3659: pop
    //   3660: aload_3
    //   3661: ldc_w 'api/ms-bank-wallet/balance'
    //   3664: invokevirtual append : (Ljava/lang/String;)Ljava/lang/StringBuilder;
    //   3667: pop
    //   3668: aload_3
    //   3669: invokevirtual toString : ()Ljava/lang/String;
    //   3672: putstatic com/laiqian/pos/hardware/RootUrlParameter.cmq : Ljava/lang/String;
    //   3675: new java/lang/StringBuilder
    //   3678: dup
    //   3679: invokespecial <init> : ()V
    //   3682: astore_3
    //   3683: aload_3
    //   3684: getstatic com/laiqian/pos/hardware/RootUrlParameter.ckS : Ljava/lang/String;
    //   3687: invokevirtual append : (Ljava/lang/String;)Ljava/lang/StringBuilder;
    //   3690: pop
    //   3691: aload_3
    //   3692: ldc_w 'api/ms-bank-wallet/token'
    //   3695: invokevirtual append : (Ljava/lang/String;)Ljava/lang/StringBuilder;
    //   3698: pop
    //   3699: aload_3
    //   3700: invokevirtual toString : ()Ljava/lang/String;
    //   3703: putstatic com/laiqian/pos/hardware/RootUrlParameter.cmr : Ljava/lang/String;
    //   3706: new java/lang/StringBuilder
    //   3709: dup
    //   3710: invokespecial <init> : ()V
    //   3713: astore_3
    //   3714: aload_3
    //   3715: getstatic com/laiqian/pos/hardware/RootUrlParameter.ckS : Ljava/lang/String;
    //   3718: invokevirtual append : (Ljava/lang/String;)Ljava/lang/StringBuilder;
    //   3721: pop
    //   3722: aload_3
    //   3723: ldc_w 'api/ms-bank-wallet/withdraw'
    //   3726: invokevirtual append : (Ljava/lang/String;)Ljava/lang/StringBuilder;
    //   3729: pop
    //   3730: aload_3
    //   3731: invokevirtual toString : ()Ljava/lang/String;
    //   3734: putstatic com/laiqian/pos/hardware/RootUrlParameter.cms : Ljava/lang/String;
    //   3737: new java/lang/StringBuilder
    //   3740: dup
    //   3741: invokespecial <init> : ()V
    //   3744: astore_3
    //   3745: aload_3
    //   3746: getstatic com/laiqian/pos/hardware/RootUrlParameter.ckP : Ljava/lang/String;
    //   3749: invokevirtual append : (Ljava/lang/String;)Ljava/lang/StringBuilder;
    //   3752: pop
    //   3753: aload_3
    //   3754: ldc_w '/message/introduction?id=2'
    //   3757: invokevirtual append : (Ljava/lang/String;)Ljava/lang/StringBuilder;
    //   3760: pop
    //   3761: aload_3
    //   3762: invokevirtual toString : ()Ljava/lang/String;
    //   3765: putstatic com/laiqian/pos/hardware/RootUrlParameter.cmt : Ljava/lang/String;
    //   3768: new java/lang/StringBuilder
    //   3771: dup
    //   3772: invokespecial <init> : ()V
    //   3775: astore_3
    //   3776: aload_3
    //   3777: getstatic com/laiqian/pos/hardware/RootUrlParameter.ckP : Ljava/lang/String;
    //   3780: invokevirtual append : (Ljava/lang/String;)Ljava/lang/StringBuilder;
    //   3783: pop
    //   3784: aload_3
    //   3785: ldc_w '/message/introduction?id=3'
    //   3788: invokevirtual append : (Ljava/lang/String;)Ljava/lang/StringBuilder;
    //   3791: pop
    //   3792: aload_3
    //   3793: invokevirtual toString : ()Ljava/lang/String;
    //   3796: putstatic com/laiqian/pos/hardware/RootUrlParameter.cmu : Ljava/lang/String;
    //   3799: new java/lang/StringBuilder
    //   3802: dup
    //   3803: invokespecial <init> : ()V
    //   3806: astore #4
    //   3808: aload #4
    //   3810: getstatic com/laiqian/pos/hardware/RootUrlParameter.ckP : Ljava/lang/String;
    //   3813: invokevirtual append : (Ljava/lang/String;)Ljava/lang/StringBuilder;
    //   3816: pop
    //   3817: aload #4
    //   3819: ldc_w '/message/introduction?id='
    //   3822: invokevirtual append : (Ljava/lang/String;)Ljava/lang/StringBuilder;
    //   3825: pop
    //   3826: invokestatic zR : ()Lcom/laiqian/c/a;
    //   3829: invokevirtual Ag : ()Z
    //   3832: ifeq -> 3842
    //   3835: ldc_w '5'
    //   3838: astore_3
    //   3839: goto -> 3862
    //   3842: invokestatic zR : ()Lcom/laiqian/c/a;
    //   3845: invokevirtual Ah : ()Z
    //   3848: ifeq -> 3858
    //   3851: ldc_w '6'
    //   3854: astore_3
    //   3855: goto -> 3862
    //   3858: ldc_w '4'
    //   3861: astore_3
    //   3862: aload #4
    //   3864: aload_3
    //   3865: invokevirtual append : (Ljava/lang/String;)Ljava/lang/StringBuilder;
    //   3868: pop
    //   3869: aload #4
    //   3871: invokevirtual toString : ()Ljava/lang/String;
    //   3874: putstatic com/laiqian/pos/hardware/RootUrlParameter.cmv : Ljava/lang/String;
    //   3877: invokestatic zi : ()Ljava/lang/String;
    //   3880: astore_3
    //   3881: aload_3
    //   3882: invokevirtual hashCode : ()I
    //   3885: istore_2
    //   3886: iload_2
    //   3887: ldc_w -1159930917
    //   3890: if_icmpeq -> 3960
    //   3893: iload_2
    //   3894: ldc_w -1102662825
    //   3897: if_icmpeq -> 3945
    //   3900: iload_2
    //   3901: ldc_w -319595696
    //   3904: if_icmpeq -> 3932
    //   3907: iload_2
    //   3908: ldc_w -190625801
    //   3911: if_icmpeq -> 3917
    //   3914: goto -> 3975
    //   3917: aload_3
    //   3918: ldc_w 'lightsblue'
    //   3921: invokevirtual equals : (Ljava/lang/Object;)Z
    //   3924: ifeq -> 3975
    //   3927: iconst_1
    //   3928: istore_0
    //   3929: goto -> 3977
    //   3932: aload_3
    //   3933: ldc_w 'zhenzhu'
    //   3936: invokevirtual equals : (Ljava/lang/Object;)Z
    //   3939: ifeq -> 3975
    //   3942: goto -> 3977
    //   3945: aload_3
    //   3946: ldc_w 'linnuo'
    //   3949: invokevirtual equals : (Ljava/lang/Object;)Z
    //   3952: ifeq -> 3975
    //   3955: iconst_2
    //   3956: istore_0
    //   3957: goto -> 3977
    //   3960: aload_3
    //   3961: ldc_w 'jindou'
    //   3964: invokevirtual equals : (Ljava/lang/Object;)Z
    //   3967: ifeq -> 3975
    //   3970: iconst_0
    //   3971: istore_0
    //   3972: goto -> 3977
    //   3975: iconst_m1
    //   3976: istore_0
    //   3977: iload_0
    //   3978: tableswitch default -> 4008, 0 -> 4028, 1 -> 4025, 2 -> 4019, 3 -> 4013
    //   4008: iconst_4
    //   4009: istore_1
    //   4010: goto -> 4028
    //   4013: bipush #8
    //   4015: istore_1
    //   4016: goto -> 4028
    //   4019: bipush #7
    //   4021: istore_1
    //   4022: goto -> 4028
    //   4025: bipush #6
    //   4027: istore_1
    //   4028: new java/lang/StringBuilder
    //   4031: dup
    //   4032: invokespecial <init> : ()V
    //   4035: astore_3
    //   4036: aload_3
    //   4037: getstatic com/laiqian/pos/hardware/RootUrlParameter.ckP : Ljava/lang/String;
    //   4040: invokevirtual append : (Ljava/lang/String;)Ljava/lang/StringBuilder;
    //   4043: pop
    //   4044: aload_3
    //   4045: ldc_w '/message/introduction?id='
    //   4048: invokevirtual append : (Ljava/lang/String;)Ljava/lang/StringBuilder;
    //   4051: pop
    //   4052: aload_3
    //   4053: iload_1
    //   4054: invokevirtual append : (I)Ljava/lang/StringBuilder;
    //   4057: pop
    //   4058: aload_3
    //   4059: invokevirtual toString : ()Ljava/lang/String;
    //   4062: putstatic com/laiqian/pos/hardware/RootUrlParameter.cmv : Ljava/lang/String;
    //   4065: new java/lang/StringBuilder
    //   4068: dup
    //   4069: invokespecial <init> : ()V
    //   4072: astore_3
    //   4073: aload_3
    //   4074: getstatic com/laiqian/pos/hardware/RootUrlParameter.ckS : Ljava/lang/String;
    //   4077: invokevirtual append : (Ljava/lang/String;)Ljava/lang/StringBuilder;
    //   4080: pop
    //   4081: aload_3
    //   4082: ldc_w 'auth'
    //   4085: invokevirtual append : (Ljava/lang/String;)Ljava/lang/StringBuilder;
    //   4088: pop
    //   4089: aload_3
    //   4090: invokevirtual toString : ()Ljava/lang/String;
    //   4093: putstatic com/laiqian/pos/hardware/RootUrlParameter.cmw : Ljava/lang/String;
    //   4096: new java/lang/StringBuilder
    //   4099: dup
    //   4100: invokespecial <init> : ()V
    //   4103: astore_3
    //   4104: aload_3
    //   4105: getstatic com/laiqian/pos/hardware/RootUrlParameter.ckN : Ljava/lang/String;
    //   4108: invokevirtual append : (Ljava/lang/String;)Ljava/lang/StringBuilder;
    //   4111: pop
    //   4112: aload_3
    //   4113: ldc_w '/sms/verify-discount'
    //   4116: invokevirtual append : (Ljava/lang/String;)Ljava/lang/StringBuilder;
    //   4119: pop
    //   4120: aload_3
    //   4121: invokevirtual toString : ()Ljava/lang/String;
    //   4124: putstatic com/laiqian/pos/hardware/RootUrlParameter.cmx : Ljava/lang/String;
    //   4127: new java/lang/StringBuilder
    //   4130: dup
    //   4131: invokespecial <init> : ()V
    //   4134: astore_3
    //   4135: aload_3
    //   4136: getstatic com/laiqian/pos/hardware/RootUrlParameter.ckN : Ljava/lang/String;
    //   4139: invokevirtual append : (Ljava/lang/String;)Ljava/lang/StringBuilder;
    //   4142: pop
    //   4143: aload_3
    //   4144: ldc_w '/sms/record-add'
    //   4147: invokevirtual append : (Ljava/lang/String;)Ljava/lang/StringBuilder;
    //   4150: pop
    //   4151: aload_3
    //   4152: invokevirtual toString : ()Ljava/lang/String;
    //   4155: putstatic com/laiqian/pos/hardware/RootUrlParameter.cmy : Ljava/lang/String;
    //   4158: getstatic com/laiqian/pos/hardware/RootUrlParameter.ckR : Ljava/lang/String;
    //   4161: putstatic com/laiqian/pos/hardware/RootUrlParameter.cmz : Ljava/lang/String;
    //   4164: new java/lang/StringBuilder
    //   4167: dup
    //   4168: invokespecial <init> : ()V
    //   4171: astore_3
    //   4172: aload_3
    //   4173: getstatic com/laiqian/pos/hardware/RootUrlParameter.ckY : Ljava/lang/String;
    //   4176: invokevirtual append : (Ljava/lang/String;)Ljava/lang/StringBuilder;
    //   4179: pop
    //   4180: aload_3
    //   4181: ldc_w '/account-charge/check'
    //   4184: invokevirtual append : (Ljava/lang/String;)Ljava/lang/StringBuilder;
    //   4187: pop
    //   4188: aload_3
    //   4189: invokevirtual toString : ()Ljava/lang/String;
    //   4192: putstatic com/laiqian/pos/hardware/RootUrlParameter.cmA : Ljava/lang/String;
    //   4195: new java/lang/StringBuilder
    //   4198: dup
    //   4199: invokespecial <init> : ()V
    //   4202: astore_3
    //   4203: aload_3
    //   4204: getstatic com/laiqian/pos/hardware/RootUrlParameter.ckY : Ljava/lang/String;
    //   4207: invokevirtual append : (Ljava/lang/String;)Ljava/lang/StringBuilder;
    //   4210: pop
    //   4211: aload_3
    //   4212: ldc_w '/account-charge/precreate'
    //   4215: invokevirtual append : (Ljava/lang/String;)Ljava/lang/StringBuilder;
    //   4218: pop
    //   4219: aload_3
    //   4220: invokevirtual toString : ()Ljava/lang/String;
    //   4223: putstatic com/laiqian/pos/hardware/RootUrlParameter.cmB : Ljava/lang/String;
    //   4226: return
  }
  
  public static @interface ServerType {}
}


/* Location:              F:\chrome_download\android-Decompile\dex2jar-2.0\classes-dex2jar.jar!\com\laiqian\pos\hardware\RootUrlParameter.class
 * Java compiler version: 6 (50.0)
 * JD-Core Version:       1.0.4
 */