package com.laiqian.backup;

class e implements Runnable {
  e(d paramd) {}
  
  public void run() { // Byte code:
    //   0: ldc ''
    //   2: astore_3
    //   3: aload_3
    //   4: astore #5
    //   6: aload_0
    //   7: getfield aHs : Lcom/laiqian/backup/d;
    //   10: getfield aHr : Lcom/laiqian/backup/c;
    //   13: getfield aHq : Lcom/laiqian/backup/BackUpRootActivity;
    //   16: getfield aHf : Ljava/lang/String;
    //   19: aload_0
    //   20: getfield aHs : Lcom/laiqian/backup/d;
    //   23: getfield aHr : Lcom/laiqian/backup/c;
    //   26: getfield aHq : Lcom/laiqian/backup/BackUpRootActivity;
    //   29: getfield aHf : Ljava/lang/String;
    //   32: ldc '.'
    //   34: invokevirtual lastIndexOf : (Ljava/lang/String;)I
    //   37: invokevirtual substring : (I)Ljava/lang/String;
    //   40: astore #4
    //   42: aload_3
    //   43: astore #5
    //   45: ldc '.lq507'
    //   47: aload #4
    //   49: invokevirtual equalsIgnoreCase : (Ljava/lang/String;)Z
    //   52: istore_2
    //   53: iconst_0
    //   54: istore_1
    //   55: iload_2
    //   56: ifne -> 158
    //   59: aload_3
    //   60: astore #5
    //   62: ldc '.lq508'
    //   64: aload #4
    //   66: invokevirtual equalsIgnoreCase : (Ljava/lang/String;)Z
    //   69: ifne -> 158
    //   72: aload_3
    //   73: astore #5
    //   75: aload_0
    //   76: getfield aHs : Lcom/laiqian/backup/d;
    //   79: getfield aHr : Lcom/laiqian/backup/c;
    //   82: getfield aHq : Lcom/laiqian/backup/BackUpRootActivity;
    //   85: aload_0
    //   86: getfield aHs : Lcom/laiqian/backup/d;
    //   89: getfield aHr : Lcom/laiqian/backup/c;
    //   92: getfield aHq : Lcom/laiqian/backup/BackUpRootActivity;
    //   95: getfield aHg : Ljava/lang/String;
    //   98: aload_0
    //   99: getfield aHs : Lcom/laiqian/backup/d;
    //   102: getfield aHr : Lcom/laiqian/backup/c;
    //   105: getfield aHq : Lcom/laiqian/backup/BackUpRootActivity;
    //   108: getfield aHf : Ljava/lang/String;
    //   111: invokestatic g : (Landroid/content/Context;Ljava/lang/String;Ljava/lang/String;)Ljava/lang/String;
    //   114: astore_3
    //   115: aload_3
    //   116: aload_0
    //   117: getfield aHs : Lcom/laiqian/backup/d;
    //   120: getfield aHr : Lcom/laiqian/backup/c;
    //   123: getfield aHq : Lcom/laiqian/backup/BackUpRootActivity;
    //   126: ldc 2131624357
    //   128: invokevirtual getString : (I)Ljava/lang/String;
    //   131: invokevirtual equals : (Ljava/lang/Object;)Z
    //   134: istore_1
    //   135: iload_1
    //   136: ifeq -> 150
    //   139: invokestatic Dp : ()V
    //   142: goto -> 150
    //   145: astore #4
    //   147: goto -> 451
    //   150: goto -> 456
    //   153: astore #4
    //   155: goto -> 449
    //   158: aload_3
    //   159: astore #5
    //   161: new java/lang/StringBuilder
    //   164: dup
    //   165: invokespecial <init> : ()V
    //   168: astore #4
    //   170: aload_3
    //   171: astore #5
    //   173: aload #4
    //   175: aload_0
    //   176: getfield aHs : Lcom/laiqian/backup/d;
    //   179: getfield aHr : Lcom/laiqian/backup/c;
    //   182: getfield aHq : Lcom/laiqian/backup/BackUpRootActivity;
    //   185: getfield aGK : Ljava/lang/String;
    //   188: invokevirtual append : (Ljava/lang/String;)Ljava/lang/StringBuilder;
    //   191: pop
    //   192: aload_3
    //   193: astore #5
    //   195: aload #4
    //   197: getstatic java/io/File.separator : Ljava/lang/String;
    //   200: invokevirtual append : (Ljava/lang/String;)Ljava/lang/StringBuilder;
    //   203: pop
    //   204: aload_3
    //   205: astore #5
    //   207: aload #4
    //   209: aload_0
    //   210: getfield aHs : Lcom/laiqian/backup/d;
    //   213: getfield aHr : Lcom/laiqian/backup/c;
    //   216: getfield aHq : Lcom/laiqian/backup/BackUpRootActivity;
    //   219: ldc 2131624364
    //   221: invokevirtual getString : (I)Ljava/lang/String;
    //   224: invokevirtual append : (Ljava/lang/String;)Ljava/lang/StringBuilder;
    //   227: pop
    //   228: aload_3
    //   229: astore #5
    //   231: new java/io/File
    //   234: dup
    //   235: aload #4
    //   237: invokevirtual toString : ()Ljava/lang/String;
    //   240: aload_0
    //   241: getfield aHs : Lcom/laiqian/backup/d;
    //   244: getfield aHr : Lcom/laiqian/backup/c;
    //   247: getfield aHq : Lcom/laiqian/backup/BackUpRootActivity;
    //   250: getfield aHf : Ljava/lang/String;
    //   253: invokespecial <init> : (Ljava/lang/String;Ljava/lang/String;)V
    //   256: invokestatic yY : ()Ljava/io/File;
    //   259: invokestatic b : (Ljava/io/File;Ljava/io/File;)Ljava/io/File;
    //   262: astore #4
    //   264: aload_3
    //   265: astore #5
    //   267: new java/util/ArrayList
    //   270: dup
    //   271: invokespecial <init> : ()V
    //   274: astore #6
    //   276: aload_3
    //   277: astore #5
    //   279: aload #4
    //   281: aload #6
    //   283: invokestatic c : (Ljava/io/File;Ljava/util/List;)Ljava/util/List;
    //   286: pop
    //   287: aload_3
    //   288: astore #5
    //   290: aload #6
    //   292: invokeinterface iterator : ()Ljava/util/Iterator;
    //   297: astore #4
    //   299: aload_3
    //   300: astore #5
    //   302: aload #4
    //   304: invokeinterface hasNext : ()Z
    //   309: ifeq -> 439
    //   312: aload_3
    //   313: astore #5
    //   315: aload #4
    //   317: invokeinterface next : ()Ljava/lang/Object;
    //   322: checkcast java/lang/String
    //   325: astore #7
    //   327: aload_3
    //   328: astore #5
    //   330: aload #7
    //   332: iconst_0
    //   333: aload #7
    //   335: ldc '/'
    //   337: invokevirtual lastIndexOf : (Ljava/lang/String;)I
    //   340: invokevirtual substring : (II)Ljava/lang/String;
    //   343: astore #6
    //   345: aload_3
    //   346: astore #5
    //   348: aload #7
    //   350: aload #7
    //   352: ldc '/'
    //   354: invokevirtual lastIndexOf : (Ljava/lang/String;)I
    //   357: iconst_1
    //   358: iadd
    //   359: invokevirtual substring : (I)Ljava/lang/String;
    //   362: astore #7
    //   364: aload_3
    //   365: astore #5
    //   367: aload_0
    //   368: getfield aHs : Lcom/laiqian/backup/d;
    //   371: getfield aHr : Lcom/laiqian/backup/c;
    //   374: getfield aHq : Lcom/laiqian/backup/BackUpRootActivity;
    //   377: aload #6
    //   379: aload #7
    //   381: invokestatic g : (Landroid/content/Context;Ljava/lang/String;Ljava/lang/String;)Ljava/lang/String;
    //   384: astore_3
    //   385: aload_3
    //   386: aload_0
    //   387: getfield aHs : Lcom/laiqian/backup/d;
    //   390: getfield aHr : Lcom/laiqian/backup/c;
    //   393: getfield aHq : Lcom/laiqian/backup/BackUpRootActivity;
    //   396: ldc 2131624357
    //   398: invokevirtual getString : (I)Ljava/lang/String;
    //   401: invokevirtual equals : (Ljava/lang/Object;)Z
    //   404: ifne -> 410
    //   407: goto -> 456
    //   410: aload #7
    //   412: invokestatic isEmpty : (Ljava/lang/CharSequence;)Z
    //   415: ifne -> 431
    //   418: aload #7
    //   420: ldc 'main'
    //   422: invokevirtual contains : (Ljava/lang/CharSequence;)Z
    //   425: ifeq -> 431
    //   428: invokestatic Dp : ()V
    //   431: goto -> 299
    //   434: astore #4
    //   436: goto -> 449
    //   439: iconst_1
    //   440: istore_1
    //   441: goto -> 456
    //   444: astore #4
    //   446: aload #5
    //   448: astore_3
    //   449: iconst_1
    //   450: istore_1
    //   451: aload #4
    //   453: invokestatic e : (Ljava/lang/Throwable;)V
    //   456: iload_1
    //   457: ifne -> 482
    //   460: aload_3
    //   461: aload_0
    //   462: getfield aHs : Lcom/laiqian/backup/d;
    //   465: getfield aHr : Lcom/laiqian/backup/c;
    //   468: getfield aHq : Lcom/laiqian/backup/BackUpRootActivity;
    //   471: ldc 2131624354
    //   473: invokevirtual getString : (I)Ljava/lang/String;
    //   476: invokevirtual endsWith : (Ljava/lang/String;)Z
    //   479: ifeq -> 513
    //   482: new com/laiqian/util/av
    //   485: dup
    //   486: aload_0
    //   487: getfield aHs : Lcom/laiqian/backup/d;
    //   490: getfield aHr : Lcom/laiqian/backup/c;
    //   493: getfield aHq : Lcom/laiqian/backup/BackUpRootActivity;
    //   496: invokespecial <init> : (Landroid/content/Context;)V
    //   499: astore #4
    //   501: aload #4
    //   503: iconst_1
    //   504: invokevirtual hn : (Z)Z
    //   507: pop
    //   508: aload #4
    //   510: invokevirtual close : ()V
    //   513: new android/os/Message
    //   516: dup
    //   517: invokespecial <init> : ()V
    //   520: astore #4
    //   522: iload_1
    //   523: ifeq -> 556
    //   526: invokestatic asF : ()V
    //   529: aload #4
    //   531: ldc 'success'
    //   533: putfield obj : Ljava/lang/Object;
    //   536: aload_0
    //   537: getfield aHs : Lcom/laiqian/backup/d;
    //   540: getfield aHr : Lcom/laiqian/backup/c;
    //   543: getfield aHq : Lcom/laiqian/backup/BackUpRootActivity;
    //   546: getfield aHl : Landroid/os/Handler;
    //   549: aload #4
    //   551: invokevirtual sendMessage : (Landroid/os/Message;)Z
    //   554: pop
    //   555: return
    //   556: aload #4
    //   558: aload_3
    //   559: putfield obj : Ljava/lang/Object;
    //   562: aload_0
    //   563: getfield aHs : Lcom/laiqian/backup/d;
    //   566: getfield aHr : Lcom/laiqian/backup/c;
    //   569: getfield aHq : Lcom/laiqian/backup/BackUpRootActivity;
    //   572: getfield aHl : Landroid/os/Handler;
    //   575: aload #4
    //   577: invokevirtual sendMessage : (Landroid/os/Message;)Z
    //   580: pop
    //   581: return
    // Exception table:
    //   from	to	target	type
    //   6	42	444	java/io/IOException
    //   45	53	444	java/io/IOException
    //   62	72	444	java/io/IOException
    //   75	115	444	java/io/IOException
    //   115	135	153	java/io/IOException
    //   139	142	145	java/io/IOException
    //   161	170	444	java/io/IOException
    //   173	192	444	java/io/IOException
    //   195	204	444	java/io/IOException
    //   207	228	444	java/io/IOException
    //   231	264	444	java/io/IOException
    //   267	276	444	java/io/IOException
    //   279	287	444	java/io/IOException
    //   290	299	444	java/io/IOException
    //   302	312	444	java/io/IOException
    //   315	327	444	java/io/IOException
    //   330	345	444	java/io/IOException
    //   348	364	444	java/io/IOException
    //   367	385	444	java/io/IOException
    //   385	407	434	java/io/IOException
    //   410	431	434	java/io/IOException }
}


/* Location:              F:\chrome_download\android-Decompile\dex2jar-2.0\classes-dex2jar.jar!\com\laiqian\backup\e.class
 * Java compiler version: 6 (50.0)
 * JD-Core Version:       1.0.4
 */