package com.laiqian.alipay;

import android.content.Context;
import java.util.HashMap;

public class b {
  public void a(Context paramContext, HashMap<String, String> paramHashMap, String paramString, a parama) { // Byte code:
    //   0: aload_0
    //   1: monitorenter
    //   2: aload_1
    //   3: invokestatic bH : (Landroid/content/Context;)Z
    //   6: ifne -> 15
    //   9: ldc '-1'
    //   11: astore_1
    //   12: goto -> 22
    //   15: aload_3
    //   16: aload_1
    //   17: aload_2
    //   18: invokestatic a : (Ljava/lang/String;Landroid/content/Context;Ljava/util/HashMap;)Ljava/lang/String;
    //   21: astore_1
    //   22: aload #4
    //   24: aload_1
    //   25: invokeinterface bm : (Ljava/lang/String;)V
    //   30: aload_0
    //   31: monitorexit
    //   32: return
    //   33: astore_1
    //   34: aload_0
    //   35: monitorexit
    //   36: aload_1
    //   37: athrow
    // Exception table:
    //   from	to	target	type
    //   2	9	33	finally
    //   15	22	33	finally
    //   22	30	33	finally }
}


/* Location:              F:\chrome_download\android-Decompile\dex2jar-2.0\classes-dex2jar.jar!\com\laiqian\alipay\b.class
 * Java compiler version: 6 (50.0)
 * JD-Core Version:       1.0.4
 */